{
  "events": [
    {
      "id": 401597316,
      "datetime": "2024-03-06T04:00:00.000Z",
      "neutral_site": 0,
      "is_postseason": 0,
      "home_team_name": "unlv",
      "home_team_id": 2439,
      "away_team_name": "sandiegostate",
      "away_team_id": 21,
      "home_elo_pre": 1778.1664568753,
      "away_elo_pre": 2072.327552312,
      "elo_diff": -394.1610954367,
      "elo_spread": 13.1387031812,
      "home_elo_prob": 0.3638157753,
      "away_elo_prob": 0.6361842247,
      "home_elo_post": 1811.8567669678,
      "away_elo_post": 2038.6372422195,
      "tournament_id": null,
      "str_event_id": "20240306_unlv_sandiegostate",
      "season": 2024,
      "result": true,
      "point_dif": -4,
      "home_team_score": 62,
      "away_team_score": 58
    },
    {
      "id": 401602978,
      "datetime": "2024-03-06T04:00:00.000Z",
      "neutral_site": 0,
      "is_postseason": 0,
      "home_team_name": "boisestate",
      "home_team_id": 68,
      "away_team_name": "nevada",
      "away_team_id": 2440,
      "home_elo_pre": 1947.705652766,
      "away_elo_pre": 2019.6325097818,
      "elo_diff": -171.9268570158,
      "elo_spread": 5.7308952339,
      "home_elo_prob": 0.5201892671,
      "away_elo_prob": 0.4798107329,
      "home_elo_post": 1909.8011906029,
      "away_elo_post": 2057.5369719449,
      "tournament_id": null,
      "str_event_id": "20240306_boisestate_nevada",
      "season": 2024,
      "result": false,
      "point_dif": 10,
      "home_team_score": 66,
      "away_team_score": 76
    },
    {
      "id": 401599558,
      "datetime": "2024-03-06T02:00:00.000Z",
      "neutral_site": 0,
      "is_postseason": 0,
      "home_team_name": "depaul",
      "home_team_id": 305,
      "away_team_name": "stjohns",
      "away_team_id": 2599,
      "home_elo_pre": 1182.4475347587,
      "away_elo_pre": 1853.0900033767,
      "elo_diff": -770.642468618,
      "elo_spread": 25.6880822873,
      "home_elo_prob": 0.1621331818,
      "away_elo_prob": 0.8378668182,
      "home_elo_post": 1169.5778768698,
      "away_elo_post": 1865.9596612656,
      "tournament_id": null,
      "str_event_id": "20240306_depaul_stjohns",
      "season": 2024,
      "result": false,
      "point_dif": 27,
      "home_team_score": 77,
      "away_team_score": 104
    },
    {
      "id": 401596937,
      "datetime": "2024-03-06T02:00:00.000Z",
      "neutral_site": 0,
      "is_postseason": 0,
      "home_team_name": "saintlouis",
      "home_team_id": 139,
      "away_team_name": "dayton",
      "away_team_id": 2168,
      "home_elo_pre": 1534.4354182349,
      "away_elo_pre": 2058.466884139,
      "elo_diff": -624.0314659041,
      "elo_spread": 20.8010488635,
      "home_elo_prob": 0.2278553922,
      "away_elo_prob": 0.7721446078,
      "home_elo_post": 1517.8705527855,
      "away_elo_post": 2075.0317495885,
      "tournament_id": null,
      "str_event_id": "20240306_saintlouis_dayton",
      "season": 2024,
      "result": false,
      "point_dif": 17,
      "home_team_score": 83,
      "away_team_score": 100
    },
    {
      "id": 401604230,
      "datetime": "2024-03-06T02:00:00.000Z",
      "neutral_site": 0,
      "is_postseason": 0,
      "home_team_name": "wakeforest",
      "home_team_id": 154,
      "away_team_name": "georgiatech",
      "away_team_id": 59,
      "home_elo_pre": 1864.2088746829,
      "away_elo_pre": 1534.5582096615,
      "elo_diff": 229.6506650214,
      "elo_spread": -7.6550221674,
      "home_elo_prob": 0.7749775734,
      "away_elo_prob": 0.2250224266,
      "home_elo_post": 1844.1826280992,
      "away_elo_post": 1554.5844562453,
      "tournament_id": null,
      "str_event_id": "20240306_wakeforest_georgiatech",
      "season": 2024,
      "result": false,
      "point_dif": 1,
      "home_team_score": 69,
      "away_team_score": 70
    },
    {
      "id": 401597221,
      "datetime": "2024-03-06T02:00:00.000Z",
      "neutral_site": 0,
      "is_postseason": 0,
      "home_team_name": "missouri",
      "home_team_id": 142,
      "away_team_name": "auburn",
      "away_team_id": 2,
      "home_elo_pre": 1459.3776084792,
      "away_elo_pre": 2064.4397236615,
      "elo_diff": -705.0621151823,
      "elo_spread": 23.5020705061,
      "home_elo_prob": 0.1894349932,
      "away_elo_prob": 0.8105650068,
      "home_elo_post": 1443.976267074,
      "away_elo_post": 2079.8410650667,
      "tournament_id": null,
      "str_event_id": "20240306_missouri_auburn",
      "season": 2024,
      "result": false,
      "point_dif": 27,
      "home_team_score": 74,
      "away_team_score": 101
    },
    {
      "id": 401603512,
      "datetime": "2024-03-06T02:00:00.000Z",
      "neutral_site": 0,
      "is_postseason": 0,
      "home_team_name": "kansas",
      "home_team_id": 2305,
      "away_team_name": "kansasstate",
      "away_team_id": 2306,
      "home_elo_pre": 2069.2625663349,
      "away_elo_pre": 1846.8952265519,
      "elo_diff": 122.3673397829,
      "elo_spread": -4.0789113261,
      "home_elo_prob": 0.7166384446,
      "away_elo_prob": 0.2833615554,
      "home_elo_post": 2092.5104023122,
      "away_elo_post": 1823.6473905746,
      "tournament_id": null,
      "str_event_id": "20240306_kansas_kansasstate",
      "season": 2024,
      "result": true,
      "point_dif": -22,
      "home_team_score": 90,
      "away_team_score": 68
    },
    {
      "id": 401604227,
      "datetime": "2024-03-06T02:00:00.000Z",
      "neutral_site": 0,
      "is_postseason": 0,
      "home_team_name": "pitt",
      "home_team_id": 221,
      "away_team_name": "floridastate",
      "away_team_id": 52,
      "home_elo_pre": 1943.723210984,
      "away_elo_pre": 1657.7093119636,
      "elo_diff": 186.0138990204,
      "elo_spread": -6.2004633007,
      "home_elo_prob": 0.7523224479,
      "away_elo_prob": 0.2476775521,
      "home_elo_post": 1961.2493067295,
      "away_elo_post": 1640.1832162181,
      "tournament_id": null,
      "str_event_id": "20240306_pitt_floridastate",
      "season": 2024,
      "result": true,
      "point_dif": -15,
      "home_team_score": 88,
      "away_team_score": 73
    },
    {
      "id": 401625590,
      "datetime": "2024-03-06T01:30:00.000Z",
      "neutral_site": 1,
      "is_postseason": 0,
      "home_team_name": "texasstate",
      "home_team_id": 326,
      "away_team_name": "olddominion",
      "away_team_id": 295,
      "home_elo_pre": 1605.9042088208,
      "away_elo_pre": 1327.9430201163,
      "elo_diff": 277.9611887045,
      "elo_spread": -9.2653729568,
      "home_elo_prob": 0.6899823127,
      "away_elo_prob": 0.3100176873,
      "home_elo_post": 1624.9172503343,
      "away_elo_post": 1308.9299786028,
      "tournament_id": 32.0,
      "str_event_id": "20240306_texasstate_olddominion",
      "season": 2024,
      "result": true,
      "point_dif": -9,
      "home_team_score": 92,
      "away_team_score": 83
    },
    {
      "id": 401594459,
      "datetime": "2024-03-06T01:30:00.000Z",
      "neutral_site": 0,
      "is_postseason": 0,
      "home_team_name": "wyoming",
      "home_team_id": 2751,
      "away_team_name": "airforce",
      "away_team_id": 2005,
      "home_elo_pre": 1621.0739768106,
      "away_elo_pre": 1470.8893420088,
      "elo_diff": 50.1846348018,
      "elo_spread": -1.6728211601,
      "home_elo_prob": 0.6726266731,
      "away_elo_prob": 0.3273733269,
      "home_elo_post": 1642.9868080281,
      "away_elo_post": 1448.9765107913,
      "tournament_id": null,
      "str_event_id": "20240306_wyoming_airforce",
      "season": 2024,
      "result": true,
      "point_dif": -11,
      "home_team_score": 74,
      "away_team_score": 63
    },
    {
      "id": 401603513,
      "datetime": "2024-03-06T01:00:00.000Z",
      "neutral_site": 0,
      "is_postseason": 0,
      "home_team_name": "oklahomastate",
      "home_team_id": 197,
      "away_team_name": "texastech",
      "away_team_id": 2641,
      "home_elo_pre": 1735.2481739219,
      "away_elo_pre": 1953.8775712121,
      "elo_diff": -318.6293972902,
      "elo_spread": 10.6209799097,
      "home_elo_prob": 0.4154590336,
      "away_elo_prob": 0.5845409664,
      "home_elo_post": 1701.0664069349,
      "away_elo_post": 1988.0593381991,
      "tournament_id": null,
      "str_event_id": "20240306_oklahomastate_texastech",
      "season": 2024,
      "result": false,
      "point_dif": 17,
      "home_team_score": 58,
      "away_team_score": 75
    },
    {
      "id": 401625693,
      "datetime": "2024-03-06T01:00:00.000Z",
      "neutral_site": 0,
      "is_postseason": 0,
      "home_team_name": "milwaukee",
      "home_team_id": 270,
      "away_team_name": "detroitmercy",
      "away_team_id": 2174,
      "home_elo_pre": 1545.3383940774,
      "away_elo_pre": 1065.6601992493,
      "elo_diff": 379.6781948282,
      "elo_spread": -12.6559398276,
      "home_elo_prob": 0.8413687846,
      "away_elo_prob": 0.1586312154,
      "home_elo_post": 1551.4003433047,
      "away_elo_post": 1059.598250022,
      "tournament_id": 15.0,
      "str_event_id": "20240306_milwaukee_detroitmercy",
      "season": 2024,
      "result": true,
      "point_dif": -4,
      "home_team_score": 83,
      "away_team_score": 79
    },
    {
      "id": 401625652,
      "datetime": "2024-03-06T01:00:00.000Z",
      "neutral_site": 0,
      "is_postseason": 0,
      "home_team_name": "lipscomb",
      "home_team_id": 288,
      "away_team_name": "northalabama",
      "away_team_id": 2453,
      "home_elo_pre": 1711.8862827487,
      "away_elo_pre": 1492.023538636,
      "elo_diff": 119.8627441127,
      "elo_spread": -3.9954248038,
      "home_elo_prob": 0.715172285,
      "away_elo_prob": 0.284827715,
      "home_elo_post": 1684.3053144702,
      "away_elo_post": 1519.6045069145,
      "tournament_id": 4.0,
      "str_event_id": "20240306_lipscomb_northalabama",
      "season": 2024,
      "result": false,
      "point_dif": 2,
      "home_team_score": 75,
      "away_team_score": 77
    },
    {
      "id": 401625653,
      "datetime": "2024-03-06T01:00:00.000Z",
      "neutral_site": 0,
      "is_postseason": 0,
      "home_team_name": "austinpeay",
      "home_team_id": 2046,
      "away_team_name": "northflorida",
      "away_team_id": 2454,
      "home_elo_pre": 1488.5770378524,
      "away_elo_pre": 1520.9173299323,
      "elo_diff": -132.3402920799,
      "elo_spread": 4.4113430693,
      "home_elo_prob": 0.5485317945,
      "away_elo_prob": 0.4514682055,
      "home_elo_post": 1506.792855893,
      "away_elo_post": 1502.7015118918,
      "tournament_id": 4.0,
      "str_event_id": "20240306_austinpeay_northflorida",
      "season": 2024,
      "result": true,
      "point_dif": -3,
      "home_team_score": 101,
      "away_team_score": 98
    },
    {
      "id": 401588715,
      "datetime": "2024-03-06T01:00:00.000Z",
      "neutral_site": 0,
      "is_postseason": 0,
      "home_team_name": "nillinois",
      "home_team_id": 2459,
      "away_team_name": "cmichigan",
      "away_team_id": 2117,
      "home_elo_pre": 1364.401115191,
      "away_elo_pre": 1499.0596353387,
      "elo_diff": -234.6585201477,
      "elo_spread": 7.8219506716,
      "home_elo_prob": 0.4750818502,
      "away_elo_prob": 0.5249181498,
      "home_elo_post": 1337.0972588511,
      "away_elo_post": 1526.3634916786,
      "tournament_id": null,
      "str_event_id": "20240306_nillinois_cmichigan",
      "season": 2024,
      "result": false,
      "point_dif": 6,
      "home_team_score": 63,
      "away_team_score": 69
    },
    {
      "id": 401603511,
      "datetime": "2024-03-06T01:00:00.000Z",
      "neutral_site": 0,
      "is_postseason": 0,
      "home_team_name": "oklahoma",
      "home_team_id": 201,
      "away_team_name": "cincinnati",
      "away_team_id": 2132,
      "home_elo_pre": 1921.6654832518,
      "away_elo_pre": 1838.7462611492,
      "elo_diff": -17.0807778974,
      "elo_spread": 0.5693592632,
      "home_elo_prob": 0.6286626514,
      "away_elo_prob": 0.3713373486,
      "home_elo_post": 1935.9234863216,
      "away_elo_post": 1824.4882580794,
      "tournament_id": null,
      "str_event_id": "20240306_oklahoma_cincinnati",
      "season": 2024,
      "result": true,
      "point_dif": -3,
      "home_team_score": 74,
      "away_team_score": 71
    },
    {
      "id": 401625692,
      "datetime": "2024-03-06T00:00:00.000Z",
      "neutral_site": 0,
      "is_postseason": 0,
      "home_team_name": "clevelandstate",
      "home_team_id": 325,
      "away_team_name": "iupui",
      "away_team_id": 85,
      "home_elo_pre": 1563.8374433624,
      "away_elo_pre": 995.5045123606,
      "elo_diff": 468.3329310017,
      "elo_spread": -15.6110977001,
      "home_elo_prob": 0.8725412119,
      "away_elo_prob": 0.1274587881,
      "home_elo_post": 1572.623361646,
      "away_elo_post": 986.718594077,
      "tournament_id": 15.0,
      "str_event_id": "20240306_clevelandstate_iupui",
      "season": 2024,
      "result": true,
      "point_dif": -19,
      "home_team_score": 85,
      "away_team_score": 66
    },
    {
      "id": 401588711,
      "datetime": "2024-03-06T00:00:00.000Z",
      "neutral_site": 0,
      "is_postseason": 0,
      "home_team_name": "miamioh",
      "home_team_id": 193,
      "away_team_name": "toledo",
      "away_team_id": 2649,
      "home_elo_pre": 1582.9143459629,
      "away_elo_pre": 1753.1225639506,
      "elo_diff": -270.2082179877,
      "elo_spread": 9.0069405996,
      "home_elo_prob": 0.4496523365,
      "away_elo_prob": 0.5503476635,
      "home_elo_post": 1536.4374385463,
      "away_elo_post": 1799.5994713671,
      "tournament_id": null,
      "str_event_id": "20240306_miamioh_toledo",
      "season": 2024,
      "result": false,
      "point_dif": 34,
      "home_team_score": 63,
      "away_team_score": 97
    },
    {
      "id": 401581251,
      "datetime": "2024-03-06T00:00:00.000Z",
      "neutral_site": 0,
      "is_postseason": 0,
      "home_team_name": "newhampshire",
      "home_team_id": 160,
      "away_team_name": "vermont",
      "away_team_id": 261,
      "home_elo_pre": 1437.9788766465,
      "away_elo_pre": 2063.5614096192,
      "elo_diff": -725.5825329727,
      "elo_spread": 24.1860844324,
      "home_elo_prob": 0.1805318772,
      "away_elo_prob": 0.8194681228,
      "home_elo_post": 1430.9430889912,
      "away_elo_post": 2070.5971972745,
      "tournament_id": null,
      "str_event_id": "20240306_newhampshire_vermont",
      "season": 2024,
      "result": false,
      "point_dif": 4,
      "home_team_score": 64,
      "away_team_score": 68
    },
    {
      "id": 401581758,
      "datetime": "2024-03-06T00:00:00.000Z",
      "neutral_site": 0,
      "is_postseason": 0,
      "home_team_name": "dartmouth",
      "home_team_id": 159,
      "away_team_name": "harvard",
      "away_team_id": 108,
      "home_elo_pre": 1212.378740789,
      "away_elo_pre": 1575.2886079825,
      "elo_diff": -462.9098671935,
      "elo_spread": 15.4303289065,
      "home_elo_prob": 0.3193598071,
      "away_elo_prob": 0.6806401929,
      "home_elo_post": 1260.6022059192,
      "away_elo_post": 1527.0651428523,
      "tournament_id": null,
      "str_event_id": "20240306_dartmouth_harvard",
      "season": 2024,
      "result": true,
      "point_dif": -7,
      "home_team_score": 76,
      "away_team_score": 69
    },
    {
      "id": 401588710,
      "datetime": "2024-03-06T00:00:00.000Z",
      "neutral_site": 0,
      "is_postseason": 0,
      "home_team_name": "wmichigan",
      "home_team_id": 2711,
      "away_team_name": "bowlinggreen",
      "away_team_id": 189,
      "home_elo_pre": 1391.2714650221,
      "away_elo_pre": 1543.919173549,
      "elo_diff": -252.647708527,
      "elo_spread": 8.4215902842,
      "home_elo_prob": 0.4621892518,
      "away_elo_prob": 0.5378107482,
      "home_elo_post": 1361.5174931731,
      "away_elo_post": 1573.673145398,
      "tournament_id": null,
      "str_event_id": "20240306_wmichigan_bowlinggreen",
      "season": 2024,
      "result": false,
      "point_dif": 8,
      "home_team_score": 65,
      "away_team_score": 73
    },
    {
      "id": 401597223,
      "datetime": "2024-03-06T00:00:00.000Z",
      "neutral_site": 0,
      "is_postseason": 0,
      "home_team_name": "georgia",
      "home_team_id": 61,
      "away_team_name": "olemiss",
      "away_team_id": 145,
      "home_elo_pre": 1583.2992938983,
      "away_elo_pre": 1808.2700427802,
      "elo_diff": -324.9707488818,
      "elo_spread": 10.8323582961,
      "home_elo_prob": 0.4110334654,
      "away_elo_prob": 0.5889665346,
      "home_elo_post": 1609.2689254281,
      "away_elo_post": 1782.3004112504,
      "tournament_id": null,
      "str_event_id": "20240306_georgia_olemiss",
      "season": 2024,
      "result": true,
      "point_dif": -3,
      "home_team_score": 69,
      "away_team_score": 66
    },
    {
      "id": 401588712,
      "datetime": "2024-03-06T00:00:00.000Z",
      "neutral_site": 0,
      "is_postseason": 0,
      "home_team_name": "akron",
      "home_team_id": 2006,
      "away_team_name": "emichigan",
      "away_team_id": 2199,
      "home_elo_pre": 1891.7210586626,
      "away_elo_pre": 1278.6302038141,
      "elo_diff": 513.0908548485,
      "elo_spread": -17.1030284949,
      "home_elo_prob": 0.886193982,
      "away_elo_prob": 0.113806018,
      "home_elo_post": 1864.4555401905,
      "away_elo_post": 1305.8957222862,
      "tournament_id": null,
      "str_event_id": "20240306_akron_emichigan",
      "season": 2024,
      "result": false,
      "point_dif": 1,
      "home_team_score": 60,
      "away_team_score": 61
    },
    {
      "id": 401588713,
      "datetime": "2024-03-06T00:00:00.000Z",
      "neutral_site": 0,
      "is_postseason": 0,
      "home_team_name": "ballstate",
      "home_team_id": 2050,
      "away_team_name": "kentstate",
      "away_team_id": 2309,
      "home_elo_pre": 1457.5491392425,
      "away_elo_pre": 1643.5611471433,
      "elo_diff": -286.0120079008,
      "elo_spread": 9.5337335967,
      "home_elo_prob": 0.4384235517,
      "away_elo_prob": 0.5615764483,
      "home_elo_post": 1494.0074901837,
      "away_elo_post": 1607.1027962021,
      "tournament_id": null,
      "str_event_id": "20240306_ballstate_kentstate",
      "season": 2024,
      "result": true,
      "point_dif": -7,
      "home_team_score": 76,
      "away_team_score": 69
    },
    {
      "id": 401596936,
      "datetime": "2024-03-06T00:00:00.000Z",
      "neutral_site": 0,
      "is_postseason": 0,
      "home_team_name": "vcu",
      "home_team_id": 2670,
      "away_team_name": "duquesne",
      "away_team_id": 2184,
      "home_elo_pre": 1910.4002470711,
      "away_elo_pre": 1771.4380237931,
      "elo_diff": 38.962223278,
      "elo_spread": -1.2987407759,
      "home_elo_prob": 0.6654748019,
      "away_elo_prob": 0.3345251981,
      "home_elo_post": 1856.6946186328,
      "away_elo_post": 1825.1436522315,
      "tournament_id": null,
      "str_event_id": "20240306_vcu_duquesne",
      "season": 2024,
      "result": false,
      "point_dif": 10,
      "home_team_score": 59,
      "away_team_score": 69
    },
    {
      "id": 401588714,
      "datetime": "2024-03-06T00:00:00.000Z",
      "neutral_site": 0,
      "is_postseason": 0,
      "home_team_name": "buffalo",
      "home_team_id": 2084,
      "away_team_name": "ohio",
      "away_team_id": 195,
      "home_elo_pre": 1150.5791485729,
      "away_elo_pre": 1775.3312300319,
      "elo_diff": -724.752081459,
      "elo_spread": 24.1584027153,
      "home_elo_prob": 0.1808857584,
      "away_elo_prob": 0.8191142416,
      "home_elo_post": 1139.3408617382,
      "away_elo_post": 1786.5695168665,
      "tournament_id": null,
      "str_event_id": "20240306_buffalo_ohio",
      "season": 2024,
      "result": false,
      "point_dif": 12,
      "home_team_score": 66,
      "away_team_score": 78
    },
    {
      "id": 401581249,
      "datetime": "2024-03-06T00:00:00.000Z",
      "neutral_site": 0,
      "is_postseason": 0,
      "home_team_name": "umbc",
      "home_team_id": 2378,
      "away_team_name": "binghamton",
      "away_team_id": 2066,
      "home_elo_pre": 1459.0313074248,
      "away_elo_pre": 1454.6669595447,
      "elo_diff": -95.6356521199,
      "elo_spread": 3.1878550707,
      "home_elo_prob": 0.5745365669,
      "away_elo_prob": 0.4254634331,
      "home_elo_post": 1446.4891775603,
      "away_elo_post": 1467.2090894092,
      "tournament_id": null,
      "str_event_id": "20240306_umbc_binghamton",
      "season": 2024,
      "result": false,
      "point_dif": 1,
      "home_team_score": 71,
      "away_team_score": 72
    },
    {
      "id": 401599559,
      "datetime": "2024-03-06T00:00:00.000Z",
      "neutral_site": 0,
      "is_postseason": 0,
      "home_team_name": "georgetown",
      "home_team_id": 46,
      "away_team_name": "providence",
      "away_team_id": 2507,
      "home_elo_pre": 1332.4478660206,
      "away_elo_pre": 1758.5694616291,
      "elo_diff": -526.1215956085,
      "elo_spread": 17.5373865203,
      "home_elo_prob": 0.2811724286,
      "away_elo_prob": 0.7188275714,
      "home_elo_post": 1313.0608378781,
      "away_elo_post": 1777.9564897716,
      "tournament_id": null,
      "str_event_id": "20240306_georgetown_providence",
      "season": 2024,
      "result": false,
      "point_dif": 13,
      "home_team_score": 58,
      "away_team_score": 71
    },
    {
      "id": 401604228,
      "datetime": "2024-03-06T00:00:00.000Z",
      "neutral_site": 0,
      "is_postseason": 0,
      "home_team_name": "clemson",
      "home_team_id": 228,
      "away_team_name": "syracuse",
      "away_team_id": 183,
      "home_elo_pre": 2052.1368691704,
      "away_elo_pre": 1821.2214813168,
      "elo_diff": 130.9153878536,
      "elo_spread": -4.3638462618,
      "home_elo_prob": 0.7216078365,
      "away_elo_prob": 0.2783921635,
      "home_elo_post": 2072.2652466159,
      "away_elo_post": 1801.0931038714,
      "tournament_id": null,
      "str_event_id": "20240306_clemson_syracuse",
      "season": 2024,
      "result": true,
      "point_dif": -15,
      "home_team_score": 90,
      "away_team_score": 75
    },
    {
      "id": 401625655,
      "datetime": "2024-03-06T00:00:00.000Z",
      "neutral_site": 0,
      "is_postseason": 0,
      "home_team_name": "ekentucky",
      "home_team_id": 2198,
      "away_team_name": "jacksonville",
      "away_team_id": 294,
      "home_elo_pre": 1789.4208614947,
      "away_elo_pre": 1510.5764082013,
      "elo_diff": 178.8444532935,
      "elo_spread": -5.9614817764,
      "home_elo_prob": 0.7484574111,
      "away_elo_prob": 0.2515425889,
      "home_elo_post": 1759.6213983373,
      "away_elo_post": 1540.3758713586,
      "tournament_id": 4.0,
      "str_event_id": "20240306_ekentucky_jacksonville",
      "season": 2024,
      "result": false,
      "point_dif": 2,
      "home_team_score": 65,
      "away_team_score": 67
    },
    {
      "id": 401625702,
      "datetime": "2024-03-06T00:00:00.000Z",
      "neutral_site": 0,
      "is_postseason": 0,
      "home_team_name": "navy",
      "home_team_id": 2426,
      "away_team_name": "loyolamd",
      "away_team_id": 2352,
      "home_elo_pre": 1399.2584933099,
      "away_elo_pre": 1156.0826273986,
      "elo_diff": 143.1758659113,
      "elo_spread": -4.7725288637,
      "home_elo_prob": 0.7286412083,
      "away_elo_prob": 0.2713587917,
      "home_elo_post": 1419.2106899927,
      "away_elo_post": 1136.1304307158,
      "tournament_id": 26.0,
      "str_event_id": "20240306_navy_loyolamd",
      "season": 2024,
      "result": true,
      "point_dif": -16,
      "home_team_score": 64,
      "away_team_score": 48
    },
    {
      "id": 401602169,
      "datetime": "2024-03-06T00:00:00.000Z",
      "neutral_site": 0,
      "is_postseason": 0,
      "home_team_name": "southflorida",
      "home_team_id": 58,
      "away_team_name": "tulane",
      "away_team_id": 2655,
      "home_elo_pre": 1950.6614462021,
      "away_elo_pre": 1605.3681423778,
      "elo_diff": 245.2933038243,
      "elo_spread": -8.1764434608,
      "home_elo_prob": 0.7827317287,
      "away_elo_prob": 0.2172682713,
      "home_elo_post": 1964.9673479031,
      "away_elo_post": 1591.0622406768,
      "tournament_id": null,
      "str_event_id": "20240306_southflorida_tulane",
      "season": 2024,
      "result": true,
      "point_dif": -13,
      "home_team_score": 85,
      "away_team_score": 72
    },
    {
      "id": 401597222,
      "datetime": "2024-03-06T00:00:00.000Z",
      "neutral_site": 0,
      "is_postseason": 0,
      "home_team_name": "florida",
      "home_team_id": 57,
      "away_team_name": "alabama",
      "away_team_id": 333,
      "home_elo_pre": 1967.6389845936,
      "away_elo_pre": 2106.4473810406,
      "elo_diff": -238.808396447,
      "elo_spread": 7.9602798816,
      "home_elo_prob": 0.4721041122,
      "away_elo_prob": 0.5278958878,
      "home_elo_post": 2015.1070466271,
      "away_elo_post": 2058.979319007,
      "tournament_id": null,
      "str_event_id": "20240306_florida_alabama",
      "season": 2024,
      "result": true,
      "point_dif": -18,
      "home_team_score": 105,
      "away_team_score": 87
    },
    {
      "id": 401600423,
      "datetime": "2024-03-06T00:00:00.000Z",
      "neutral_site": 0,
      "is_postseason": 0,
      "home_team_name": "illinois",
      "home_team_id": 356,
      "away_team_name": "purdue",
      "away_team_id": 2509,
      "home_elo_pre": 2062.0964846916,
      "away_elo_pre": 2239.6375447694,
      "elo_diff": -277.5410600778,
      "elo_spread": 9.2513686693,
      "home_elo_prob": 0.4444351704,
      "away_elo_prob": 0.5555648296,
      "home_elo_post": 2037.0348772533,
      "away_elo_post": 2264.6991522077,
      "tournament_id": null,
      "str_event_id": "20240306_illinois_purdue",
      "season": 2024,
      "result": false,
      "point_dif": 6,
      "home_team_score": 71,
      "away_team_score": 77
    },
    {
      "id": 401581248,
      "datetime": "2024-03-06T00:00:00.000Z",
      "neutral_site": 0,
      "is_postseason": 0,
      "home_team_name": "bryant",
      "home_team_id": 2803,
      "away_team_name": "ualbany",
      "away_team_id": 399,
      "home_elo_pre": 1661.9775145761,
      "away_elo_pre": 1382.089011725,
      "elo_diff": 179.8885028512,
      "elo_spread": -5.9962834284,
      "home_elo_prob": 0.7490227397,
      "away_elo_prob": 0.2509772603,
      "home_elo_post": 1672.31111347,
      "away_elo_post": 1371.7554128311,
      "tournament_id": null,
      "str_event_id": "20240306_bryant_ualbany",
      "season": 2024,
      "result": true,
      "point_dif": -4,
      "home_team_score": 83,
      "away_team_score": 79
    },
    {
      "id": 401604229,
      "datetime": "2024-03-06T00:00:00.000Z",
      "neutral_site": 0,
      "is_postseason": 0,
      "home_team_name": "louisville",
      "home_team_id": 97,
      "away_team_name": "virginiatech",
      "away_team_id": 259,
      "home_elo_pre": 1371.5642317492,
      "away_elo_pre": 1764.6621000254,
      "elo_diff": -493.0978682762,
      "elo_spread": 16.4365956092,
      "home_elo_prob": 0.3007763931,
      "away_elo_prob": 0.6992236069,
      "home_elo_post": 1349.0048271262,
      "away_elo_post": 1787.2215046483,
      "tournament_id": null,
      "str_event_id": "20240306_louisville_virginiatech",
      "season": 2024,
      "result": false,
      "point_dif": 16,
      "home_team_score": 64,
      "away_team_score": 80
    },
    {
      "id": 401604226,
      "datetime": "2024-03-06T00:00:00.000Z",
      "neutral_site": 0,
      "is_postseason": 0,
      "home_team_name": "northcarolina",
      "home_team_id": 153,
      "away_team_name": "notredame",
      "away_team_id": 87,
      "home_elo_pre": 2136.5904407166,
      "away_elo_pre": 1534.5810866938,
      "elo_diff": 502.0093540227,
      "elo_spread": -16.7336451341,
      "home_elo_prob": 0.8829373869,
      "away_elo_prob": 0.1170626131,
      "home_elo_post": 2145.9788076063,
      "away_elo_post": 1525.1927198041,
      "tournament_id": null,
      "str_event_id": "20240306_northcarolina_notredame",
      "season": 2024,
      "result": true,
      "point_dif": -33,
      "home_team_score": 84,
      "away_team_score": 51
    },
    {
      "id": 401573645,
      "datetime": "2024-03-06T00:00:00.000Z",
      "neutral_site": 0,
      "is_postseason": 0,
      "home_team_name": "mtsu",
      "home_team_id": 2393,
      "away_team_name": "liberty",
      "away_team_id": 2335,
      "home_elo_pre": 1475.3528559371,
      "away_elo_pre": 1705.5594911901,
      "elo_diff": -330.206635253,
      "elo_spread": 11.0068878418,
      "home_elo_prob": 0.4073901764,
      "away_elo_prob": 0.5926098236,
      "home_elo_post": 1516.8731327121,
      "away_elo_post": 1664.039214415,
      "tournament_id": null,
      "str_event_id": "20240306_mtsu_liberty",
      "season": 2024,
      "result": true,
      "point_dif": -8,
      "home_team_score": 69,
      "away_team_score": 61
    },
    {
      "id": 401581250,
      "datetime": "2024-03-05T23:00:00.000Z",
      "neutral_site": 0,
      "is_postseason": 0,
      "home_team_name": "maine",
      "home_team_id": 311,
      "away_team_name": "umasslowell",
      "away_team_id": 2349,
      "home_elo_pre": 1485.7536311819,
      "away_elo_pre": 1847.0828839054,
      "elo_diff": -461.3292527236,
      "elo_spread": 15.3776417575,
      "home_elo_prob": 0.3203495122,
      "away_elo_prob": 0.6796504878,
      "home_elo_post": 1530.7780685368,
      "away_elo_post": 1802.0584465505,
      "tournament_id": null,
      "str_event_id": "20240305_maine_umasslowell",
      "season": 2024,
      "result": true,
      "point_dif": -6,
      "home_team_score": 71,
      "away_team_score": 65
    },
    {
      "id": 401625701,
      "datetime": "2024-03-05T23:00:00.000Z",
      "neutral_site": 0,
      "is_postseason": 0,
      "home_team_name": "army",
      "home_team_id": 349,
      "away_team_name": "holycross",
      "away_team_id": 107,
      "home_elo_pre": 1259.4836756162,
      "away_elo_pre": 1179.0963445834,
      "elo_diff": -19.6126689672,
      "elo_spread": 0.6537556322,
      "home_elo_prob": 0.6269598559,
      "away_elo_prob": 0.3730401441,
      "home_elo_post": 1201.4346596924,
      "away_elo_post": 1237.1453605072,
      "tournament_id": 26.0,
      "str_event_id": "20240305_army_holycross",
      "season": 2024,
      "result": false,
      "point_dif": 16,
      "home_team_score": 68,
      "away_team_score": 84
    },
    {
      "id": 401625589,
      "datetime": "2024-03-05T23:00:00.000Z",
      "neutral_site": 1,
      "is_postseason": 0,
      "home_team_name": "ulmonroe",
      "home_team_id": 2433,
      "away_team_name": "coastalcar",
      "away_team_id": 324,
      "home_elo_pre": 1364.802114898,
      "away_elo_pre": 1299.2804366205,
      "elo_diff": 65.5216782774,
      "elo_spread": -2.1840559426,
      "home_elo_prob": 0.5470074022,
      "away_elo_prob": 0.4529925978,
      "home_elo_post": 1337.5801407029,
      "away_elo_post": 1326.5024108156,
      "tournament_id": 32.0,
      "str_event_id": "20240305_ulmonroe_coastalcar",
      "season": 2024,
      "result": false,
      "point_dif": 4,
      "home_team_score": 71,
      "away_team_score": 75
    },
    {
      "id": 401573467,
      "datetime": "2024-03-05T03:00:00.000Z",
      "neutral_site": 0,
      "is_postseason": 0,
      "home_team_name": "portlandstate",
      "home_team_id": 2502,
      "away_team_name": "idaho",
      "away_team_id": 70,
      "home_elo_pre": 1468.2545535569,
      "away_elo_pre": 1381.641533752,
      "elo_diff": -13.3869801952,
      "elo_spread": 0.4462326732,
      "home_elo_prob": 0.6311411424,
      "away_elo_prob": 0.3688588576,
      "home_elo_post": 1496.5363895355,
      "away_elo_post": 1353.3596977734,
      "tournament_id": null,
      "str_event_id": "20240305_portlandstate_idaho",
      "season": 2024,
      "result": true,
      "point_dif": -15,
      "home_team_score": 72,
      "away_team_score": 57
    },
    {
      "id": 401573469,
      "datetime": "2024-03-05T02:00:00.000Z",
      "neutral_site": 0,
      "is_postseason": 0,
      "home_team_name": "montanastate",
      "home_team_id": 147,
      "away_team_name": "weberstate",
      "away_team_id": 2692,
      "home_elo_pre": 1519.4713317449,
      "away_elo_pre": 1823.4234629053,
      "elo_diff": -403.9521311604,
      "elo_spread": 13.4650710387,
      "home_elo_prob": 0.3573185701,
      "away_elo_prob": 0.6426814299,
      "home_elo_post": 1573.9777355582,
      "away_elo_post": 1768.917059092,
      "tournament_id": null,
      "str_event_id": "20240305_montanastate_weberstate",
      "season": 2024,
      "result": true,
      "point_dif": -12,
      "home_team_score": 76,
      "away_team_score": 64
    },
    {
      "id": 401573468,
      "datetime": "2024-03-05T02:00:00.000Z",
      "neutral_site": 0,
      "is_postseason": 0,
      "home_team_name": "montana",
      "home_team_id": 149,
      "away_team_name": "idahostate",
      "away_team_id": 304,
      "home_elo_pre": 1729.1147800632,
      "away_elo_pre": 1480.5925154124,
      "elo_diff": 148.5222646509,
      "elo_spread": -4.950742155,
      "home_elo_prob": 0.7316730799,
      "away_elo_prob": 0.2683269201,
      "home_elo_post": 1747.9329098778,
      "away_elo_post": 1461.7743855978,
      "tournament_id": null,
      "str_event_id": "20240305_montana_idahostate",
      "season": 2024,
      "result": true,
      "point_dif": -14,
      "home_team_score": 79,
      "away_team_score": 65
    },
    {
      "id": 401573466,
      "datetime": "2024-03-05T02:00:00.000Z",
      "neutral_site": 0,
      "is_postseason": 0,
      "home_team_name": "sacramentostate",
      "home_team_id": 16,
      "away_team_name": "ewashington",
      "away_team_id": 331,
      "home_elo_pre": 1263.7123181188,
      "away_elo_pre": 1832.8535997433,
      "elo_diff": -669.1412816245,
      "elo_spread": 22.3047093875,
      "home_elo_prob": 0.2058217953,
      "away_elo_prob": 0.7941782047,
      "home_elo_post": 1256.656957898,
      "away_elo_post": 1839.908959964,
      "tournament_id": null,
      "str_event_id": "20240305_sacramentostate_ewashington",
      "season": 2024,
      "result": false,
      "point_dif": 3,
      "home_team_score": 88,
      "away_team_score": 91
    },
    {
      "id": 401603510,
      "datetime": "2024-03-05T02:00:00.000Z",
      "neutral_site": 0,
      "is_postseason": 0,
      "home_team_name": "baylor",
      "home_team_id": 239,
      "away_team_name": "texas",
      "away_team_id": 251,
      "home_elo_pre": 2033.485853818,
      "away_elo_pre": 1947.6039759154,
      "elo_diff": -14.1181220974,
      "elo_spread": 0.4706040699,
      "home_elo_prob": 0.6306510999,
      "away_elo_prob": 0.3693489001,
      "home_elo_post": 2055.9353322444,
      "away_elo_post": 1925.1544974889,
      "tournament_id": null,
      "str_event_id": "20240305_baylor_texas",
      "season": 2024,
      "result": true,
      "point_dif": -8,
      "home_team_score": 93,
      "away_team_score": 85
    },
    {
      "id": 401598914,
      "datetime": "2024-03-05T02:00:00.000Z",
      "neutral_site": 0,
      "is_postseason": 0,
      "home_team_name": "southern",
      "home_team_id": 2582,
      "away_team_name": "floridaam",
      "away_team_id": 50,
      "home_elo_pre": 1548.271866212,
      "away_elo_pre": 1123.9012327821,
      "elo_diff": 324.3706334298,
      "elo_spread": -10.8123544477,
      "home_elo_prob": 0.8189515137,
      "away_elo_prob": 0.1810484863,
      "home_elo_post": 1560.1494842305,
      "away_elo_post": 1112.0236147636,
      "tournament_id": null,
      "str_event_id": "20240305_southern_floridaam",
      "season": 2024,
      "result": true,
      "point_dif": -14,
      "home_team_score": 58,
      "away_team_score": 44
    },
    {
      "id": 401574643,
      "datetime": "2024-03-05T01:30:00.000Z",
      "neutral_site": 0,
      "is_postseason": 0,
      "home_team_name": "grambling",
      "home_team_id": 2755,
      "away_team_name": "bethune",
      "away_team_id": 2065,
      "home_elo_pre": 1573.3223265958,
      "away_elo_pre": 1451.05011748,
      "elo_diff": 22.2722091159,
      "elo_spread": -0.7424069705,
      "home_elo_prob": 0.6546971364,
      "away_elo_prob": 0.3453028636,
      "home_elo_post": 1594.9862373391,
      "away_elo_post": 1429.3862067367,
      "tournament_id": null,
      "str_event_id": "20240305_grambling_bethune",
      "season": 2024,
      "result": true,
      "point_dif": -9,
      "home_team_score": 69,
      "away_team_score": 60
    },
    {
      "id": 401602354,
      "datetime": "2024-03-05T01:30:00.000Z",
      "neutral_site": 0,
      "is_postseason": 0,
      "home_team_name": "texassouthern",
      "home_team_id": 2640,
      "away_team_name": "alcornstate",
      "away_team_id": 2016,
      "home_elo_pre": 1475.1375531579,
      "away_elo_pre": 1508.5098480273,
      "elo_diff": -133.3722948694,
      "elo_spread": 4.4457431623,
      "home_elo_prob": 0.5477960994,
      "away_elo_prob": 0.4522039006,
      "home_elo_post": 1451.6438391902,
      "away_elo_post": 1532.003561995,
      "tournament_id": null,
      "str_event_id": "20240305_texassouthern_alcornstate",
      "season": 2024,
      "result": false,
      "point_dif": 3,
      "home_team_score": 79,
      "away_team_score": 82
    },
    {
      "id": 401583833,
      "datetime": "2024-03-05T01:30:00.000Z",
      "neutral_site": 0,
      "is_postseason": 0,
      "home_team_name": "prairieview",
      "home_team_id": 2504,
      "away_team_name": "jacksonstate",
      "away_team_id": 2296,
      "home_elo_pre": 1265.4351612219,
      "away_elo_pre": 1373.8698917825,
      "elo_diff": -208.4347305606,
      "elo_spread": 6.947824352,
      "home_elo_prob": 0.4939310216,
      "away_elo_prob": 0.5060689784,
      "home_elo_post": 1238.9863973969,
      "away_elo_post": 1400.3186556075,
      "tournament_id": null,
      "str_event_id": "20240305_prairieview_jacksonstate",
      "season": 2024,
      "result": false,
      "point_dif": 5,
      "home_team_score": 74,
      "away_team_score": 79
    },
    {
      "id": 401573470,
      "datetime": "2024-03-05T01:00:00.000Z",
      "neutral_site": 0,
      "is_postseason": 0,
      "home_team_name": "narizona",
      "home_team_id": 2464,
      "away_team_name": "ncolorado",
      "away_team_id": 2458,
      "home_elo_pre": 1347.3536654037,
      "away_elo_pre": 1687.0757972675,
      "elo_diff": -439.7221318638,
      "elo_spread": 14.6574043955,
      "home_elo_prob": 0.3340384658,
      "away_elo_prob": 0.6659615342,
      "home_elo_post": 1327.4984547899,
      "away_elo_post": 1706.9310078814,
      "tournament_id": null,
      "str_event_id": "20240305_narizona_ncolorado",
      "season": 2024,
      "result": false,
      "point_dif": 8,
      "home_team_score": 74,
      "away_team_score": 82
    },
    {
      "id": 401579054,
      "datetime": "2024-03-05T01:00:00.000Z",
      "neutral_site": 0,
      "is_postseason": 0,
      "home_team_name": "texasamcc",
      "home_team_id": 357,
      "away_team_name": "neworleans",
      "away_team_id": 2443,
      "home_elo_pre": 1780.8974322989,
      "away_elo_pre": 1234.0769030511,
      "elo_diff": 446.8205292478,
      "elo_spread": -14.8940176416,
      "home_elo_prob": 0.8654948732,
      "away_elo_prob": 0.1345051268,
      "home_elo_post": 1789.1268955343,
      "away_elo_post": 1225.8474398157,
      "tournament_id": null,
      "str_event_id": "20240305_texasamcc_neworleans",
      "season": 2024,
      "result": true,
      "point_dif": -13,
      "home_team_score": 73,
      "away_team_score": 60
    },
    {
      "id": 401578980,
      "datetime": "2024-03-05T01:00:00.000Z",
      "neutral_site": 0,
      "is_postseason": 0,
      "home_team_name": "mcneese",
      "home_team_id": 2377,
      "away_team_name": "houchristian",
      "away_team_id": 2277,
      "home_elo_pre": 1943.2800605308,
      "away_elo_pre": 1106.0171095496,
      "elo_diff": 737.2629509812,
      "elo_spread": -24.5754316994,
      "home_elo_prob": 0.9368884024,
      "away_elo_prob": 0.0631115976,
      "home_elo_post": 1947.1894122701,
      "away_elo_post": 1102.1077578104,
      "tournament_id": null,
      "str_event_id": "20240305_mcneese_houchristian",
      "season": 2024,
      "result": true,
      "point_dif": -18,
      "home_team_score": 87,
      "away_team_score": 69
    },
    {
      "id": 401579090,
      "datetime": "2024-03-05T01:00:00.000Z",
      "neutral_site": 0,
      "is_postseason": 0,
      "home_team_name": "texasamcomm",
      "home_team_id": 2837,
      "away_team_name": "lamar",
      "away_team_id": 2320,
      "home_elo_pre": 1330.7512891605,
      "away_elo_pre": 1602.545174992,
      "elo_diff": -371.7938858315,
      "elo_spread": 12.3931295277,
      "home_elo_prob": 0.3788428696,
      "away_elo_prob": 0.6211571304,
      "home_elo_post": 1300.280772863,
      "away_elo_post": 1633.0156912895,
      "tournament_id": null,
      "str_event_id": "20240305_texasamcomm_lamar",
      "season": 2024,
      "result": false,
      "point_dif": 17,
      "home_team_score": 53,
      "away_team_score": 70
    },
    {
      "id": 401589751,
      "datetime": "2024-03-05T00:50:00.000Z",
      "neutral_site": 0,
      "is_postseason": 0,
      "home_team_name": "coppinstate",
      "home_team_id": 2154,
      "away_team_name": "scstate",
      "away_team_id": 2569,
      "home_elo_pre": 1052.6408115608,
      "away_elo_pre": 1439.2738472208,
      "elo_diff": -486.63303566,
      "elo_spread": 16.2211011887,
      "home_elo_prob": 0.304704137,
      "away_elo_prob": 0.695295863,
      "home_elo_post": 1041.4292516,
      "away_elo_post": 1450.4854071815,
      "tournament_id": null,
      "str_event_id": "20240305_coppinstate_scstate",
      "season": 2024,
      "result": false,
      "point_dif": 3,
      "home_team_score": 58,
      "away_team_score": 61
    },
    {
      "id": 401579065,
      "datetime": "2024-03-05T00:30:00.000Z",
      "neutral_site": 0,
      "is_postseason": 0,
      "home_team_name": "nwesternstate",
      "home_team_id": 2466,
      "away_team_name": "nicholls",
      "away_team_id": 2447,
      "home_elo_pre": 1377.2458354501,
      "away_elo_pre": 1531.1373980415,
      "elo_diff": -253.8915625914,
      "elo_spread": 8.4630520864,
      "home_elo_prob": 0.4612994665,
      "away_elo_prob": 0.5387005335,
      "home_elo_post": 1350.9603105886,
      "away_elo_post": 1557.422922903,
      "tournament_id": null,
      "str_event_id": "20240305_nwesternstate_nicholls",
      "season": 2024,
      "result": false,
      "point_dif": 6,
      "home_team_score": 62,
      "away_team_score": 68
    },
    {
      "id": 401594416,
      "datetime": "2024-03-05T00:30:00.000Z",
      "neutral_site": 0,
      "is_postseason": 0,
      "home_team_name": "norfolkstate",
      "home_team_id": 2450,
      "away_team_name": "mdeastern",
      "away_team_id": 2379,
      "home_elo_pre": 1632.997176762,
      "away_elo_pre": 1308.9149366722,
      "elo_diff": 224.0822400899,
      "elo_spread": -7.469408003,
      "home_elo_prob": 0.7721703183,
      "away_elo_prob": 0.2278296817,
      "home_elo_post": 1650.1635991869,
      "away_elo_post": 1291.7485142473,
      "tournament_id": null,
      "str_event_id": "20240305_norfolkstate_mdeastern",
      "season": 2024,
      "result": true,
      "point_dif": -19,
      "home_team_score": 69,
      "away_team_score": 50
    },
    {
      "id": 401604433,
      "datetime": "2024-03-05T00:30:00.000Z",
      "neutral_site": 0,
      "is_postseason": 0,
      "home_team_name": "howard",
      "home_team_id": 47,
      "away_team_name": "delawarestate",
      "away_team_id": 2169,
      "home_elo_pre": 1577.7716381427,
      "away_elo_pre": 1432.9207640989,
      "elo_diff": 44.8508740437,
      "elo_spread": -1.4950291348,
      "home_elo_prob": 0.6692372911,
      "away_elo_prob": 0.3307627089,
      "home_elo_post": 1604.5208567317,
      "away_elo_post": 1406.1715455099,
      "tournament_id": null,
      "str_event_id": "20240305_howard_delawarestate",
      "season": 2024,
      "result": true,
      "point_dif": -19,
      "home_team_score": 85,
      "away_team_score": 66
    },
    {
      "id": 401606725,
      "datetime": "2024-03-05T00:30:00.000Z",
      "neutral_site": 0,
      "is_postseason": 0,
      "home_team_name": "morganstate",
      "home_team_id": 2415,
      "away_team_name": "nccentral",
      "away_team_id": 2428,
      "home_elo_pre": 1368.3521272538,
      "away_elo_pre": 1640.5189080833,
      "elo_diff": -372.1667808295,
      "elo_spread": 12.405559361,
      "home_elo_prob": 0.3785903377,
      "away_elo_prob": 0.6214096623,
      "home_elo_post": 1414.9220366341,
      "away_elo_post": 1593.9489987029,
      "tournament_id": null,
      "str_event_id": "20240305_morganstate_nccentral",
      "season": 2024,
      "result": true,
      "point_dif": -9,
      "home_team_score": 88,
      "away_team_score": 79
    },
    {
      "id": 401604225,
      "datetime": "2024-03-05T00:00:00.000Z",
      "neutral_site": 0,
      "is_postseason": 0,
      "home_team_name": "ncstate",
      "home_team_id": 152,
      "away_team_name": "duke",
      "away_team_id": 150,
      "home_elo_pre": 1757.0588611723,
      "away_elo_pre": 2138.8570268704,
      "elo_diff": -481.7981656981,
      "elo_spread": 16.0599388566,
      "home_elo_prob": 0.307660334,
      "away_elo_prob": 0.692339666,
      "home_elo_post": 1734.3740882748,
      "away_elo_post": 2161.5417997679,
      "tournament_id": null,
      "str_event_id": "20240305_ncstate_duke",
      "season": 2024,
      "result": false,
      "point_dif": 15,
      "home_team_score": 64,
      "away_team_score": 79
    },
    {
      "id": 401625651,
      "datetime": "2024-03-05T00:00:00.000Z",
      "neutral_site": 0,
      "is_postseason": 0,
      "home_team_name": "kennesawstate",
      "home_team_id": 338,
      "away_team_name": "jacksonville",
      "away_team_id": 294,
      "home_elo_pre": 1553.3565267489,
      "away_elo_pre": 1470.5561064193,
      "elo_diff": -17.1995796704,
      "elo_spread": 0.5733193223,
      "home_elo_prob": 0.6285828236,
      "away_elo_prob": 0.3714171764,
      "home_elo_post": 1513.3362249669,
      "away_elo_post": 1510.5764082013,
      "tournament_id": 4.0,
      "str_event_id": "20240305_kennesawstate_jacksonville",
      "season": 2024,
      "result": false,
      "point_dif": 6,
      "home_team_score": 86,
      "away_team_score": 92
    },
    {
      "id": 401607459,
      "datetime": "2024-03-04T02:00:00.000Z",
      "neutral_site": 0,
      "is_postseason": 0,
      "home_team_name": "colorado",
      "home_team_id": 38,
      "away_team_name": "stanford",
      "away_team_id": 24,
      "home_elo_pre": 1860.8038354696,
      "away_elo_pre": 1654.2968607253,
      "elo_diff": 106.5069747444,
      "elo_spread": -3.5502324915,
      "home_elo_prob": 0.7072774912,
      "away_elo_prob": 0.2927225088,
      "home_elo_post": 1879.2863624253,
      "away_elo_post": 1635.8143337695,
      "tournament_id": null,
      "str_event_id": "20240304_colorado_stanford",
      "season": 2024,
      "result": true,
      "point_dif": -10,
      "home_team_score": 81,
      "away_team_score": 71
    }
  ],
  "lastupdated": "2024-03-06T09:08:07.132056"
}