{
  "events": [
    {
      "id": 401696658,
      "datetime": "2025-08-09T23:15:00.000Z",
      "neutral_site": 0,
      "is_postseason": 0,
      "home_team_name": "cardinals",
      "home_team_id": 24,
      "away_team_name": "cubs",
      "away_team_id": 16,
      "home_elo_pre": 1494.3331702721,
      "away_elo_pre": 1559.9454660896,
      "elo_diff": -15.6122958175,
      "elo_spread": 1.2489836654,
      "home_elo_prob": 0.4887679401,
      "away_elo_prob": 0.5112320599,
      "home_elo_post": 1489.0013429222,
      "away_elo_post": 1565.2772934395,
      "tournament_id": null,
      "str_event_id": "20250809_cardinals_cubs",
      "season": 2025,
      "result": false,
      "point_dif": 8,
      "home_team_score": 1,
      "away_team_score": 9
    },
    {
      "id": 401696662,
      "datetime": "2025-08-09T23:15:00.000Z",
      "neutral_site": 0,
      "is_postseason": 0,
      "home_team_name": "rangers",
      "home_team_id": 13,
      "away_team_name": "phillies",
      "away_team_id": 22,
      "home_elo_pre": 1542.7944139623,
      "away_elo_pre": 1569.4947631868,
      "elo_diff": 23.2996507755,
      "elo_spread": -1.863972062,
      "home_elo_prob": 0.516759166,
      "away_elo_prob": 0.483240834,
      "home_elo_post": 1540.9842926244,
      "away_elo_post": 1571.3048845247,
      "tournament_id": null,
      "str_event_id": "20250809_rangers_phillies",
      "season": 2025,
      "result": false,
      "point_dif": 1,
      "home_team_score": 2,
      "away_team_score": 3
    },
    {
      "id": 401696656,
      "datetime": "2025-08-09T23:15:00.000Z",
      "neutral_site": 0,
      "is_postseason": 0,
      "home_team_name": "braves",
      "home_team_id": 15,
      "away_team_name": "marlins",
      "away_team_id": 28,
      "home_elo_pre": 1487.0895848912,
      "away_elo_pre": 1480.1855928464,
      "elo_diff": 56.9039920448,
      "elo_spread": -4.5523193636,
      "home_elo_prob": 0.5408544284,
      "away_elo_prob": 0.4591455716,
      "home_elo_post": 1489.5481088953,
      "away_elo_post": 1477.7270688423,
      "tournament_id": null,
      "str_event_id": "20250809_braves_marlins",
      "season": 2025,
      "result": true,
      "point_dif": -2,
      "home_team_score": 8,
      "away_team_score": 6
    },
    {
      "id": 401696659,
      "datetime": "2025-08-09T23:10:00.000Z",
      "neutral_site": 0,
      "is_postseason": 0,
      "home_team_name": "whitesox",
      "home_team_id": 4,
      "away_team_name": "guardians",
      "away_team_id": 5,
      "home_elo_pre": 1408.0131840439,
      "away_elo_pre": 1520.8139408685,
      "elo_diff": -62.8007568246,
      "elo_spread": 5.024060546,
      "home_elo_prob": 0.4549338578,
      "away_elo_prob": 0.5450661422,
      "home_elo_post": 1405.5835599696,
      "away_elo_post": 1523.2435649428,
      "tournament_id": null,
      "str_event_id": "20250809_whitesox_guardians",
      "season": 2025,
      "result": false,
      "point_dif": 2,
      "home_team_score": 1,
      "away_team_score": 3
    },
    {
      "id": 401696661,
      "datetime": "2025-08-09T23:10:00.000Z",
      "neutral_site": 0,
      "is_postseason": 0,
      "home_team_name": "brewers",
      "home_team_id": 8,
      "away_team_name": "mets",
      "away_team_id": 21,
      "home_elo_pre": 1603.1980527732,
      "away_elo_pre": 1524.7139851962,
      "elo_diff": 128.484067577,
      "elo_spread": -10.2787254062,
      "home_elo_prob": 0.5914123114,
      "away_elo_prob": 0.4085876886,
      "home_elo_post": 1605.8738928112,
      "away_elo_post": 1522.0381451582,
      "tournament_id": null,
      "str_event_id": "20250809_brewers_mets",
      "season": 2025,
      "result": true,
      "point_dif": -3,
      "home_team_score": 7,
      "away_team_score": 4
    },
    {
      "id": 401696660,
      "datetime": "2025-08-09T23:10:00.000Z",
      "neutral_site": 0,
      "is_postseason": 0,
      "home_team_name": "twins",
      "home_team_id": 9,
      "away_team_name": "royals",
      "away_team_id": 7,
      "home_elo_pre": 1485.8076827431,
      "away_elo_pre": 1513.048323341,
      "elo_diff": 22.7593594021,
      "elo_spread": -1.8207487522,
      "home_elo_prob": 0.5163708218,
      "away_elo_prob": 0.4836291782,
      "home_elo_post": 1482.9415757461,
      "away_elo_post": 1515.914430338,
      "tournament_id": null,
      "str_event_id": "20250809_twins_royals",
      "season": 2025,
      "result": false,
      "point_dif": 2,
      "home_team_score": 0,
      "away_team_score": 2
    },
    {
      "id": 401696657,
      "datetime": "2025-08-09T23:05:00.000Z",
      "neutral_site": 0,
      "is_postseason": 0,
      "home_team_name": "orioles",
      "home_team_id": 1,
      "away_team_name": "athletics",
      "away_team_id": 11,
      "home_elo_pre": 1477.7479154596,
      "away_elo_pre": 1450.5129698429,
      "elo_diff": 77.2349456167,
      "elo_spread": -6.1787956493,
      "home_elo_prob": 0.5553472722,
      "away_elo_prob": 0.4446527278,
      "home_elo_post": 1471.424818421,
      "away_elo_post": 1456.8360668814,
      "tournament_id": null,
      "str_event_id": "20250809_orioles_athletics",
      "season": 2025,
      "result": false,
      "point_dif": 8,
      "home_team_score": 3,
      "away_team_score": 11
    },
    {
      "id": 401696654,
      "datetime": "2025-08-09T22:40:00.000Z",
      "neutral_site": 0,
      "is_postseason": 0,
      "home_team_name": "pirates",
      "home_team_id": 23,
      "away_team_name": "reds",
      "away_team_id": 17,
      "home_elo_pre": 1460.0319963913,
      "away_elo_pre": 1513.3549918255,
      "elo_diff": -3.3229954342,
      "elo_spread": 0.2658396347,
      "home_elo_prob": 0.4976089308,
      "away_elo_prob": 0.5023910692,
      "home_elo_post": 1458.3100162235,
      "away_elo_post": 1515.0769719934,
      "tournament_id": null,
      "str_event_id": "20250809_pirates_reds",
      "season": 2025,
      "result": false,
      "point_dif": 1,
      "home_team_score": 1,
      "away_team_score": 2
    },
    {
      "id": 401696653,
      "datetime": "2025-08-09T22:10:00.000Z",
      "neutral_site": 0,
      "is_postseason": 0,
      "home_team_name": "tigers",
      "home_team_id": 6,
      "away_team_name": "angels",
      "away_team_id": 3,
      "home_elo_pre": 1514.6543471332,
      "away_elo_pre": 1444.4087427481,
      "elo_diff": 120.2456043851,
      "elo_spread": -9.6196483508,
      "home_elo_prob": 0.5856702274,
      "away_elo_prob": 0.4143297726,
      "home_elo_post": 1510.3600782093,
      "away_elo_post": 1448.7030116719,
      "tournament_id": null,
      "str_event_id": "20250809_tigers_angels",
      "season": 2025,
      "result": false,
      "point_dif": 3,
      "home_team_score": 4,
      "away_team_score": 7
    },
    {
      "id": 401696667,
      "datetime": "2025-08-09T20:05:00.000Z",
      "neutral_site": 0,
      "is_postseason": 0,
      "home_team_name": "giants",
      "home_team_id": 26,
      "away_team_name": "nationals",
      "away_team_id": 20,
      "home_elo_pre": 1507.672635947,
      "away_elo_pre": 1410.5159294494,
      "elo_diff": 147.1567064976,
      "elo_spread": -11.7725365198,
      "home_elo_prob": 0.6043326715,
      "away_elo_prob": 0.3956673285,
      "home_elo_post": 1504.1150335151,
      "away_elo_post": 1414.0735318812,
      "tournament_id": null,
      "str_event_id": "20250809_giants_nationals",
      "season": 2025,
      "result": false,
      "point_dif": 2,
      "home_team_score": 2,
      "away_team_score": 4
    },
    {
      "id": 401696655,
      "datetime": "2025-08-09T18:05:00.000Z",
      "neutral_site": 0,
      "is_postseason": 0,
      "home_team_name": "yankees",
      "home_team_id": 10,
      "away_team_name": "astros",
      "away_team_id": 18,
      "home_elo_pre": 1544.490533236,
      "away_elo_pre": 1524.9540020706,
      "elo_diff": 69.5365311653,
      "elo_spread": -5.5629224932,
      "home_elo_prob": 0.5498692001,
      "away_elo_prob": 0.4501307999,
      "home_elo_post": 1546.0027696754,
      "away_elo_post": 1523.4417656313,
      "tournament_id": null,
      "str_event_id": "20250809_yankees_astros",
      "season": 2025,
      "result": true,
      "point_dif": -1,
      "home_team_score": 5,
      "away_team_score": 4
    },
    {
      "id": 401696651,
      "datetime": "2025-08-09T02:10:00.000Z",
      "neutral_site": 0,
      "is_postseason": 0,
      "home_team_name": "dodgers",
      "home_team_id": 19,
      "away_team_name": "bluejays",
      "away_team_id": 14,
      "home_elo_pre": 1583.1277586782,
      "away_elo_pre": 1557.6695604223,
      "elo_diff": 75.4581982559,
      "elo_spread": -6.0366558605,
      "home_elo_prob": 0.5540841104,
      "away_elo_prob": 0.4459158896,
      "home_elo_post": 1586.5971317169,
      "away_elo_post": 1554.2001873837,
      "tournament_id": null,
      "str_event_id": "20250809_dodgers_bluejays",
      "season": 2025,
      "result": true,
      "point_dif": -4,
      "home_team_score": 5,
      "away_team_score": 1
    },
    {
      "id": 401696650,
      "datetime": "2025-08-09T01:40:00.000Z",
      "neutral_site": 0,
      "is_postseason": 0,
      "home_team_name": "mariners",
      "home_team_id": 12,
      "away_team_name": "rays",
      "away_team_id": 30,
      "home_elo_pre": 1514.0169992442,
      "away_elo_pre": 1509.0764157693,
      "elo_diff": 54.9405834748,
      "elo_spread": -4.395246678,
      "home_elo_prob": 0.5394507543,
      "away_elo_prob": 0.4605492457,
      "home_elo_post": 1515.5742520377,
      "away_elo_post": 1507.5191629758,
      "tournament_id": null,
      "str_event_id": "20250809_mariners_rays",
      "season": 2025,
      "result": true,
      "point_dif": -1,
      "home_team_score": 3,
      "away_team_score": 2
    },
    {
      "id": 401696649,
      "datetime": "2025-08-09T01:40:00.000Z",
      "neutral_site": 0,
      "is_postseason": 0,
      "home_team_name": "diamondbacks",
      "home_team_id": 29,
      "away_team_name": "rockies",
      "away_team_id": 27,
      "home_elo_pre": 1503.5929756216,
      "away_elo_pre": 1346.3423278705,
      "elo_diff": 207.250647751,
      "elo_spread": -16.5800518201,
      "home_elo_prob": 0.6448586612,
      "away_elo_prob": 0.3551413388,
      "home_elo_post": 1506.5006937817,
      "away_elo_post": 1343.4346097104,
      "tournament_id": null,
      "str_event_id": "20250809_diamondbacks_rockies",
      "season": 2025,
      "result": true,
      "point_dif": -5,
      "home_team_score": 6,
      "away_team_score": 1
    },
    {
      "id": 401696648,
      "datetime": "2025-08-09T01:40:00.000Z",
      "neutral_site": 0,
      "is_postseason": 0,
      "home_team_name": "padres",
      "home_team_id": 25,
      "away_team_name": "redsox",
      "away_team_id": 2,
      "home_elo_pre": 1540.816173664,
      "away_elo_pre": 1557.6492113904,
      "elo_diff": 33.1669622736,
      "elo_spread": -2.6533569819,
      "home_elo_prob": 0.5238474403,
      "away_elo_prob": 0.4761525597,
      "home_elo_post": 1534.973030719,
      "away_elo_post": 1563.4923543354,
      "tournament_id": null,
      "str_event_id": "20250809_padres_redsox",
      "season": 2025,
      "result": false,
      "point_dif": 8,
      "home_team_score": 2,
      "away_team_score": 10
    },
    {
      "id": 401696644,
      "datetime": "2025-08-08T23:40:00.000Z",
      "neutral_site": 0,
      "is_postseason": 0,
      "home_team_name": "whitesox",
      "home_team_id": 4,
      "away_team_name": "guardians",
      "away_team_id": 5,
      "home_elo_pre": 1411.6244117727,
      "away_elo_pre": 1517.2027131397,
      "elo_diff": -55.578301367,
      "elo_spread": 4.4462641094,
      "home_elo_prob": 0.4600932606,
      "away_elo_prob": 0.5399067394,
      "home_elo_post": 1408.0131840439,
      "away_elo_post": 1520.8139408685,
      "tournament_id": null,
      "str_event_id": "20250808_whitesox_guardians",
      "season": 2025,
      "result": false,
      "point_dif": 4,
      "home_team_score": 5,
      "away_team_score": 9
    },
    {
      "id": 401696641,
      "datetime": "2025-08-08T23:15:00.000Z",
      "neutral_site": 0,
      "is_postseason": 0,
      "home_team_name": "braves",
      "home_team_id": 15,
      "away_team_name": "marlins",
      "away_team_id": 28,
      "home_elo_pre": 1491.6303103556,
      "away_elo_pre": 1475.6448673819,
      "elo_diff": 65.9854429737,
      "elo_spread": -5.2788354379,
      "home_elo_prob": 0.5473381373,
      "away_elo_prob": 0.4526618627,
      "home_elo_post": 1487.0895848912,
      "away_elo_post": 1480.1855928464,
      "tournament_id": null,
      "str_event_id": "20250808_braves_marlins",
      "season": 2025,
      "result": false,
      "point_dif": 4,
      "home_team_score": 1,
      "away_team_score": 5
    },
    {
      "id": 401696638,
      "datetime": "2025-08-08T23:10:00.000Z",
      "neutral_site": 0,
      "is_postseason": 0,
      "home_team_name": "tigers",
      "home_team_id": 6,
      "away_team_name": "angels",
      "away_team_id": 3,
      "home_elo_pre": 1513.2849004713,
      "away_elo_pre": 1445.7781894099,
      "elo_diff": 117.5067110613,
      "elo_spread": -9.4005368849,
      "home_elo_prob": 0.58375601,
      "away_elo_prob": 0.41624399,
      "home_elo_post": 1514.6543471332,
      "away_elo_post": 1444.4087427481,
      "tournament_id": null,
      "str_event_id": "20250808_tigers_angels",
      "season": 2025,
      "result": true,
      "point_dif": -1,
      "home_team_score": 6,
      "away_team_score": 5
    },
    {
      "id": 401696640,
      "datetime": "2025-08-08T23:05:00.000Z",
      "neutral_site": 0,
      "is_postseason": 0,
      "home_team_name": "yankees",
      "home_team_id": 10,
      "away_team_name": "astros",
      "away_team_id": 18,
      "home_elo_pre": 1547.644387237,
      "away_elo_pre": 1521.8001480696,
      "elo_diff": 75.8442391674,
      "elo_spread": -6.0675391334,
      "home_elo_prob": 0.5543586225,
      "away_elo_prob": 0.4456413775,
      "home_elo_post": 1544.490533236,
      "away_elo_post": 1524.9540020706,
      "tournament_id": null,
      "str_event_id": "20250808_yankees_astros",
      "season": 2025,
      "result": false,
      "point_dif": 2,
      "home_team_score": 3,
      "away_team_score": 5
    },
    {
      "id": 401696642,
      "datetime": "2025-08-08T23:05:00.000Z",
      "neutral_site": 0,
      "is_postseason": 0,
      "home_team_name": "orioles",
      "home_team_id": 1,
      "away_team_name": "athletics",
      "away_team_id": 11,
      "home_elo_pre": 1476.2500300186,
      "away_elo_pre": 1452.0108552838,
      "elo_diff": 74.2391747348,
      "elo_spread": -5.9391339788,
      "home_elo_prob": 0.5532170519,
      "away_elo_prob": 0.4467829481,
      "home_elo_post": 1477.7479154596,
      "away_elo_post": 1450.5129698429,
      "tournament_id": null,
      "str_event_id": "20250808_orioles_athletics",
      "season": 2025,
      "result": true,
      "point_dif": -1,
      "home_team_score": 3,
      "away_team_score": 2
    },
    {
      "id": 401696639,
      "datetime": "2025-08-08T22:40:00.000Z",
      "neutral_site": 0,
      "is_postseason": 0,
      "home_team_name": "pirates",
      "home_team_id": 23,
      "away_team_name": "reds",
      "away_team_id": 17,
      "home_elo_pre": 1458.2766345096,
      "away_elo_pre": 1515.1103537073,
      "elo_diff": -6.8337191977,
      "elo_spread": 0.5466975358,
      "home_elo_prob": 0.4950829023,
      "away_elo_prob": 0.5049170977,
      "home_elo_post": 1460.0319963913,
      "away_elo_post": 1513.3549918255,
      "tournament_id": null,
      "str_event_id": "20250808_pirates_reds",
      "season": 2025,
      "result": true,
      "point_dif": -1,
      "home_team_score": 3,
      "away_team_score": 2
    }
  ],
  "lastupdated": "2025-08-10T09:11:29.505095"
}