{
  "events": [
    {
      "id": 401802843,
      "datetime": "2025-12-12T03:00:00.000Z",
      "neutral_site": 0,
      "is_postseason": 0,
      "home_team_name": "canucks",
      "home_team_id": 22,
      "away_team_name": "sabres",
      "away_team_id": 2,
      "home_elo_pre": 1463.7592423207,
      "away_elo_pre": 1466.3083121117,
      "elo_diff": 22.4509302091,
      "elo_spread": -1.1454556229,
      "home_elo_prob": 0.5161491239,
      "away_elo_prob": 0.4838508761,
      "home_elo_post": 1460.8675946683,
      "away_elo_post": 1469.1999597641,
      "tournament_id": null,
      "str_event_id": "20251212_canucks_sabres",
      "season": 2026,
      "result": false,
      "point_dif": 1,
      "home_team_score": 2,
      "away_team_score": 3
    },
    {
      "id": 401802841,
      "datetime": "2025-12-12T02:30:00.000Z",
      "neutral_site": 0,
      "is_postseason": 0,
      "home_team_name": "avalanche",
      "home_team_id": 17,
      "away_team_name": "panthers",
      "away_team_id": 26,
      "home_elo_pre": 1619.4372840455,
      "away_elo_pre": 1570.2398622549,
      "elo_diff": 74.1974217906,
      "elo_spread": -3.7855827444,
      "home_elo_prob": 0.5531873484,
      "away_elo_prob": 0.4468126516,
      "home_elo_post": 1625.0025278426,
      "away_elo_post": 1564.6746184578,
      "tournament_id": null,
      "str_event_id": "20251212_avalanche_panthers",
      "season": 2026,
      "result": true,
      "point_dif": -4,
      "home_team_score": 6,
      "away_team_score": 2
    },
    {
      "id": 401802842,
      "datetime": "2025-12-12T02:00:00.000Z",
      "neutral_site": 0,
      "is_postseason": 0,
      "home_team_name": "oilers",
      "home_team_id": 6,
      "away_team_name": "redwings",
      "away_team_id": 5,
      "home_elo_pre": 1549.3104242676,
      "away_elo_pre": 1491.3069285475,
      "elo_diff": 83.0034957202,
      "elo_spread": -4.2348722306,
      "home_elo_prob": 0.5594433585,
      "away_elo_prob": 0.4405566415,
      "home_elo_post": 1554.0187153094,
      "away_elo_post": 1486.5986375057,
      "tournament_id": null,
      "str_event_id": "20251212_oilers_redwings",
      "season": 2026,
      "result": true,
      "point_dif": -3,
      "home_team_score": 4,
      "away_team_score": 1
    },
    {
      "id": 401802839,
      "datetime": "2025-12-12T01:00:00.000Z",
      "neutral_site": 0,
      "is_postseason": 0,
      "home_team_name": "wild",
      "home_team_id": 30,
      "away_team_name": "stars",
      "away_team_id": 9,
      "home_elo_pre": 1515.3632783625,
      "away_elo_pre": 1589.9736303047,
      "elo_diff": -49.6103519422,
      "elo_spread": 2.5311404052,
      "home_elo_prob": 0.4643630119,
      "away_elo_prob": 0.5356369881,
      "home_elo_post": 1521.4407301626,
      "away_elo_post": 1583.8961785047,
      "tournament_id": null,
      "str_event_id": "20251212_wild_stars",
      "season": 2026,
      "result": true,
      "point_dif": -3,
      "home_team_score": 5,
      "away_team_score": 2
    },
    {
      "id": 401802840,
      "datetime": "2025-12-12T01:00:00.000Z",
      "neutral_site": 0,
      "is_postseason": 0,
      "home_team_name": "jets",
      "home_team_id": 28,
      "away_team_name": "bruins",
      "away_team_id": 1,
      "home_elo_pre": 1558.3416717441,
      "away_elo_pre": 1508.9012743668,
      "elo_diff": 74.4403973772,
      "elo_spread": -3.797979458,
      "home_elo_prob": 0.5533601986,
      "away_elo_prob": 0.4466398014,
      "home_elo_post": 1551.989784859,
      "away_elo_post": 1515.2531612519,
      "tournament_id": null,
      "str_event_id": "20251212_jets_bruins",
      "season": 2026,
      "result": false,
      "point_dif": 3,
      "home_team_score": 3,
      "away_team_score": 6
    },
    {
      "id": 401802838,
      "datetime": "2025-12-12T01:00:00.000Z",
      "neutral_site": 0,
      "is_postseason": 0,
      "home_team_name": "predators",
      "home_team_id": 27,
      "away_team_name": "blues",
      "away_team_id": 19,
      "home_elo_pre": 1433.3868868253,
      "away_elo_pre": 1480.8798052652,
      "elo_diff": -22.4929184399,
      "elo_spread": 1.1475978796,
      "home_elo_prob": 0.4838206947,
      "away_elo_prob": 0.5161793053,
      "home_elo_post": 1440.8622687975,
      "away_elo_post": 1473.404423293,
      "tournament_id": null,
      "str_event_id": "20251212_predators_blues",
      "season": 2026,
      "result": true,
      "point_dif": -5,
      "home_team_score": 7,
      "away_team_score": 2
    },
    {
      "id": 401802835,
      "datetime": "2025-12-12T00:30:00.000Z",
      "neutral_site": 0,
      "is_postseason": 0,
      "home_team_name": "penguins",
      "home_team_id": 16,
      "away_team_name": "canadiens",
      "away_team_id": 10,
      "home_elo_pre": 1488.3288694434,
      "away_elo_pre": 1465.4152042763,
      "elo_diff": 47.913665167,
      "elo_spread": -2.4445747534,
      "home_elo_prob": 0.5344221168,
      "away_elo_prob": 0.4655778832,
      "home_elo_post": 1483.5273150457,
      "away_elo_post": 1470.2167586739,
      "tournament_id": null,
      "str_event_id": "20251212_penguins_canadiens",
      "season": 2026,
      "result": false,
      "point_dif": 2,
      "home_team_score": 2,
      "away_team_score": 4
    },
    {
      "id": 401802836,
      "datetime": "2025-12-12T00:00:00.000Z",
      "neutral_site": 0,
      "is_postseason": 0,
      "home_team_name": "capitals",
      "home_team_id": 23,
      "away_team_name": "hurricanes",
      "away_team_id": 7,
      "home_elo_pre": 1565.6527517345,
      "away_elo_pre": 1572.3614155483,
      "elo_diff": 18.2913361862,
      "elo_spread": -0.9332314381,
      "home_elo_prob": 0.5131586352,
      "away_elo_prob": 0.4868413648,
      "home_elo_post": 1562.7833390485,
      "away_elo_post": 1575.2308282342,
      "tournament_id": null,
      "str_event_id": "20251212_capitals_hurricanes",
      "season": 2026,
      "result": false,
      "point_dif": 1,
      "home_team_score": 2,
      "away_team_score": 3
    },
    {
      "id": 401802833,
      "datetime": "2025-12-12T00:00:00.000Z",
      "neutral_site": 0,
      "is_postseason": 0,
      "home_team_name": "islanders",
      "home_team_id": 12,
      "away_team_name": "ducks",
      "away_team_id": 25,
      "home_elo_pre": 1489.9289601026,
      "away_elo_pre": 1475.4335266314,
      "elo_diff": 39.4954334713,
      "elo_spread": -2.0150731363,
      "home_elo_prob": 0.5283886845,
      "away_elo_prob": 0.4716113155,
      "home_elo_post": 1495.06705546,
      "away_elo_post": 1470.295431274,
      "tournament_id": null,
      "str_event_id": "20251212_islanders_ducks",
      "season": 2026,
      "result": true,
      "point_dif": -3,
      "home_team_score": 5,
      "away_team_score": 2
    },
    {
      "id": 401802831,
      "datetime": "2025-12-12T00:00:00.000Z",
      "neutral_site": 0,
      "is_postseason": 0,
      "home_team_name": "mapleleafs",
      "home_team_id": 21,
      "away_team_name": "sharks",
      "away_team_id": 18,
      "home_elo_pre": 1549.0523946041,
      "away_elo_pre": 1376.7233302269,
      "elo_diff": 197.3290643772,
      "elo_spread": -10.067809407,
      "home_elo_prob": 0.6382920231,
      "away_elo_prob": 0.3617079769,
      "home_elo_post": 1545.1642003798,
      "away_elo_post": 1380.6115244513,
      "tournament_id": null,
      "str_event_id": "20251212_mapleleafs_sharks",
      "season": 2026,
      "result": false,
      "point_dif": 1,
      "home_team_score": 2,
      "away_team_score": 3
    },
    {
      "id": 401802832,
      "datetime": "2025-12-12T00:00:00.000Z",
      "neutral_site": 0,
      "is_postseason": 0,
      "home_team_name": "devils",
      "home_team_id": 11,
      "away_team_name": "lightning",
      "away_team_id": 20,
      "home_elo_pre": 1497.5052758752,
      "away_elo_pre": 1573.8679646739,
      "elo_diff": -51.3626887987,
      "elo_spread": 2.6205453469,
      "home_elo_prob": 0.4631087377,
      "away_elo_prob": 0.5368912623,
      "home_elo_post": 1491.6785524243,
      "away_elo_post": 1579.6946881249,
      "tournament_id": null,
      "str_event_id": "20251212_devils_lightning",
      "season": 2026,
      "result": false,
      "point_dif": 4,
      "home_team_score": 4,
      "away_team_score": 8
    },
    {
      "id": 401802837,
      "datetime": "2025-12-12T00:00:00.000Z",
      "neutral_site": 0,
      "is_postseason": 0,
      "home_team_name": "bluejackets",
      "home_team_id": 29,
      "away_team_name": "senators",
      "away_team_id": 14,
      "home_elo_pre": 1472.1548923444,
      "away_elo_pre": 1496.4597467376,
      "elo_diff": 0.6951456068,
      "elo_spread": -0.0354666126,
      "home_elo_prob": 0.5005001973,
      "away_elo_prob": 0.4994998027,
      "home_elo_post": 1466.6024130881,
      "away_elo_post": 1502.0122259939,
      "tournament_id": null,
      "str_event_id": "20251212_bluejackets_senators",
      "season": 2026,
      "result": false,
      "point_dif": 3,
      "home_team_score": 3,
      "away_team_score": 6
    },
    {
      "id": 401802834,
      "datetime": "2025-12-12T00:00:00.000Z",
      "neutral_site": 0,
      "is_postseason": 0,
      "home_team_name": "flyers",
      "home_team_id": 15,
      "away_team_name": "goldenknights",
      "away_team_id": 37,
      "home_elo_pre": 1472.0942315221,
      "away_elo_pre": 1553.4882605401,
      "elo_diff": -56.394029018,
      "elo_spread": 2.8772463785,
      "home_elo_prob": 0.4595100914,
      "away_elo_prob": 0.5404899086,
      "home_elo_post": 1469.6098502857,
      "away_elo_post": 1555.9726417764,
      "tournament_id": null,
      "str_event_id": "20251212_flyers_goldenknights",
      "season": 2026,
      "result": false,
      "point_dif": 1,
      "home_team_score": 2,
      "away_team_score": 3
    },
    {
      "id": 401802830,
      "datetime": "2025-12-11T03:00:00.000Z",
      "neutral_site": 0,
      "is_postseason": 0,
      "home_team_name": "kraken",
      "home_team_id": 124292,
      "away_team_name": "kings",
      "away_team_id": 8,
      "home_elo_pre": 1455.8806215991,
      "away_elo_pre": 1541.196169349,
      "elo_diff": -60.3155477499,
      "elo_spread": 3.0773238648,
      "home_elo_prob": 0.4567081464,
      "away_elo_prob": 0.5432918536,
      "home_elo_post": 1458.9781948901,
      "away_elo_post": 1538.0985960579,
      "tournament_id": null,
      "str_event_id": "20251211_kraken_kings",
      "season": 2026,
      "result": true,
      "point_dif": -1,
      "home_team_score": 3,
      "away_team_score": 2
    },
    {
      "id": 401802829,
      "datetime": "2025-12-11T02:00:00.000Z",
      "neutral_site": 0,
      "is_postseason": 0,
      "home_team_name": "mammoth",
      "home_team_id": 129764,
      "away_team_name": "panthers",
      "away_team_id": 26,
      "home_elo_pre": 1495.2690619035,
      "away_elo_pre": 1567.7108136432,
      "elo_diff": -47.4417517397,
      "elo_spread": 2.4204975377,
      "home_elo_prob": 0.4659158586,
      "away_elo_prob": 0.5340841414,
      "home_elo_post": 1492.7400132919,
      "away_elo_post": 1570.2398622549,
      "tournament_id": null,
      "str_event_id": "20251211_mammoth_panthers",
      "season": 2026,
      "result": false,
      "point_dif": 1,
      "home_team_score": 3,
      "away_team_score": 4
    },
    {
      "id": 401802828,
      "datetime": "2025-12-11T01:30:00.000Z",
      "neutral_site": 0,
      "is_postseason": 0,
      "home_team_name": "flames",
      "home_team_id": 3,
      "away_team_name": "redwings",
      "away_team_id": 5,
      "home_elo_pre": 1483.4794479369,
      "away_elo_pre": 1488.428117516,
      "elo_diff": 20.0513304209,
      "elo_spread": -1.0230270623,
      "home_elo_prob": 0.5144240887,
      "away_elo_prob": 0.4855759113,
      "home_elo_post": 1480.6006369055,
      "away_elo_post": 1491.3069285475,
      "tournament_id": null,
      "str_event_id": "20251211_flames_redwings",
      "season": 2026,
      "result": false,
      "point_dif": 1,
      "home_team_score": 3,
      "away_team_score": 4
    },
    {
      "id": 401802827,
      "datetime": "2025-12-11T00:30:00.000Z",
      "neutral_site": 0,
      "is_postseason": 0,
      "home_team_name": "blackhawks",
      "home_team_id": 4,
      "away_team_name": "rangers",
      "away_team_id": 13,
      "home_elo_pre": 1408.9869614141,
      "away_elo_pre": 1525.4852097021,
      "elo_diff": -91.498248288,
      "elo_spread": 4.6682779739,
      "home_elo_prob": 0.4345396144,
      "away_elo_prob": 0.5654603856,
      "home_elo_post": 1415.530254045,
      "away_elo_post": 1518.9419170711,
      "tournament_id": null,
      "str_event_id": "20251211_blackhawks_rangers",
      "season": 2026,
      "result": true,
      "point_dif": -3,
      "home_team_score": 3,
      "away_team_score": 0
    },
    {
      "id": 401802826,
      "datetime": "2025-12-10T02:30:00.000Z",
      "neutral_site": 0,
      "is_postseason": 0,
      "home_team_name": "predators",
      "home_team_id": 27,
      "away_team_name": "avalanche",
      "away_team_id": 17,
      "home_elo_pre": 1429.6702763755,
      "away_elo_pre": 1623.1538944953,
      "elo_diff": -168.4836181198,
      "elo_spread": 8.5961029653,
      "home_elo_prob": 0.381087515,
      "away_elo_prob": 0.618912485,
      "home_elo_post": 1433.3868868253,
      "away_elo_post": 1619.4372840455,
      "tournament_id": null,
      "str_event_id": "20251210_predators_avalanche",
      "season": 2026,
      "result": true,
      "point_dif": -1,
      "home_team_score": 4,
      "away_team_score": 3
    },
    {
      "id": 401802825,
      "datetime": "2025-12-10T02:00:00.000Z",
      "neutral_site": 0,
      "is_postseason": 0,
      "home_team_name": "oilers",
      "home_team_id": 6,
      "away_team_name": "sabres",
      "away_team_id": 2,
      "home_elo_pre": 1552.7146470631,
      "away_elo_pre": 1462.9040893162,
      "elo_diff": 114.8105577469,
      "elo_spread": -5.8576815177,
      "home_elo_prob": 0.5818691928,
      "away_elo_prob": 0.4181308072,
      "home_elo_post": 1549.3104242676,
      "away_elo_post": 1466.3083121117,
      "tournament_id": null,
      "str_event_id": "20251210_oilers_sabres",
      "season": 2026,
      "result": false,
      "point_dif": 1,
      "home_team_score": 3,
      "away_team_score": 4
    },
    {
      "id": 401802823,
      "datetime": "2025-12-10T01:00:00.000Z",
      "neutral_site": 0,
      "is_postseason": 0,
      "home_team_name": "blues",
      "home_team_id": 19,
      "away_team_name": "bruins",
      "away_team_id": 1,
      "home_elo_pre": 1486.5118584728,
      "away_elo_pre": 1503.2692211593,
      "elo_diff": 8.2426373135,
      "elo_spread": -0.4205427201,
      "home_elo_prob": 0.5059307761,
      "away_elo_prob": 0.4940692239,
      "home_elo_post": 1480.8798052652,
      "away_elo_post": 1508.9012743668,
      "tournament_id": null,
      "str_event_id": "20251210_blues_bruins",
      "season": 2026,
      "result": false,
      "point_dif": 3,
      "home_team_score": 2,
      "away_team_score": 5
    },
    {
      "id": 401802824,
      "datetime": "2025-12-10T01:00:00.000Z",
      "neutral_site": 0,
      "is_postseason": 0,
      "home_team_name": "jets",
      "home_team_id": 28,
      "away_team_name": "stars",
      "away_team_id": 9,
      "home_elo_pre": 1561.1084968512,
      "away_elo_pre": 1587.2068051976,
      "elo_diff": -1.0983083464,
      "elo_spread": 0.0560361401,
      "home_elo_prob": 0.4992097043,
      "away_elo_prob": 0.5007902957,
      "home_elo_post": 1558.3416717441,
      "away_elo_post": 1589.9736303047,
      "tournament_id": null,
      "str_event_id": "20251210_jets_stars",
      "season": 2026,
      "result": false,
      "point_dif": 1,
      "home_team_score": 3,
      "away_team_score": 4
    },
    {
      "id": 401802822,
      "datetime": "2025-12-10T00:30:00.000Z",
      "neutral_site": 0,
      "is_postseason": 0,
      "home_team_name": "hurricanes",
      "home_team_id": 7,
      "away_team_name": "bluejackets",
      "away_team_id": 29,
      "home_elo_pre": 1567.969141429,
      "away_elo_pre": 1476.5471664636,
      "elo_diff": 116.4219749654,
      "elo_spread": -5.9398966819,
      "home_elo_prob": 0.5829971837,
      "away_elo_prob": 0.4170028163,
      "home_elo_post": 1572.3614155483,
      "away_elo_post": 1472.1548923444,
      "tournament_id": null,
      "str_event_id": "20251210_hurricanes_bluejackets",
      "season": 2026,
      "result": true,
      "point_dif": -3,
      "home_team_score": 4,
      "away_team_score": 1
    },
    {
      "id": 401802819,
      "datetime": "2025-12-10T00:00:00.000Z",
      "neutral_site": 0,
      "is_postseason": 0,
      "home_team_name": "islanders",
      "home_team_id": 12,
      "away_team_name": "goldenknights",
      "away_team_id": 37,
      "home_elo_pre": 1486.9177089103,
      "away_elo_pre": 1556.4995117324,
      "elo_diff": -44.5818028221,
      "elo_spread": 2.2745817766,
      "home_elo_prob": 0.4679647577,
      "away_elo_prob": 0.5320352423,
      "home_elo_post": 1489.9289601026,
      "away_elo_post": 1553.4882605401,
      "tournament_id": null,
      "str_event_id": "20251210_islanders_goldenknights",
      "season": 2026,
      "result": true,
      "point_dif": -1,
      "home_team_score": 5,
      "away_team_score": 4
    },
    {
      "id": 401802818,
      "datetime": "2025-12-10T00:00:00.000Z",
      "neutral_site": 0,
      "is_postseason": 0,
      "home_team_name": "senators",
      "home_team_id": 14,
      "away_team_name": "devils",
      "away_team_id": 11,
      "home_elo_pre": 1499.3909613401,
      "away_elo_pre": 1494.5740612727,
      "elo_diff": 29.8169000675,
      "elo_spread": -1.5212704116,
      "home_elo_prob": 0.5214418258,
      "away_elo_prob": 0.4785581742,
      "home_elo_post": 1496.4597467376,
      "away_elo_post": 1497.5052758752,
      "tournament_id": null,
      "str_event_id": "20251210_senators_devils",
      "season": 2026,
      "result": false,
      "point_dif": 1,
      "home_team_score": 3,
      "away_team_score": 4
    },
    {
      "id": 401802817,
      "datetime": "2025-12-10T00:00:00.000Z",
      "neutral_site": 0,
      "is_postseason": 0,
      "home_team_name": "canadiens",
      "home_team_id": 10,
      "away_team_name": "lightning",
      "away_team_id": 20,
      "home_elo_pre": 1471.6514686311,
      "away_elo_pre": 1567.6317003191,
      "elo_diff": -70.9802316879,
      "elo_spread": 3.6214403922,
      "home_elo_prob": 0.4491025224,
      "away_elo_prob": 0.5508974776,
      "home_elo_post": 1465.4152042763,
      "away_elo_post": 1573.8679646739,
      "tournament_id": null,
      "str_event_id": "20251210_canadiens_lightning",
      "season": 2026,
      "result": false,
      "point_dif": 5,
      "home_team_score": 1,
      "away_team_score": 6
    },
    {
      "id": 401802820,
      "datetime": "2025-12-10T00:00:00.000Z",
      "neutral_site": 0,
      "is_postseason": 0,
      "home_team_name": "flyers",
      "home_team_id": 15,
      "away_team_name": "sharks",
      "away_team_id": 18,
      "home_elo_pre": 1467.6561603218,
      "away_elo_pre": 1381.1614014272,
      "elo_diff": 111.4947588946,
      "elo_spread": -5.6885081069,
      "home_elo_prob": 0.5795454526,
      "away_elo_prob": 0.4204545474,
      "home_elo_post": 1472.0942315221,
      "away_elo_post": 1376.7233302269,
      "tournament_id": null,
      "str_event_id": "20251210_flyers_sharks",
      "season": 2026,
      "result": true,
      "point_dif": -3,
      "home_team_score": 4,
      "away_team_score": 1
    },
    {
      "id": 401802821,
      "datetime": "2025-12-10T00:00:00.000Z",
      "neutral_site": 0,
      "is_postseason": 0,
      "home_team_name": "penguins",
      "home_team_id": 16,
      "away_team_name": "ducks",
      "away_team_id": 25,
      "home_elo_pre": 1491.3364611715,
      "away_elo_pre": 1472.4259349032,
      "elo_diff": 43.9105262682,
      "elo_spread": -2.2403329729,
      "home_elo_prob": 0.5315541732,
      "away_elo_prob": 0.4684458268,
      "home_elo_post": 1488.3288694434,
      "away_elo_post": 1475.4335266314,
      "tournament_id": null,
      "str_event_id": "20251210_penguins_ducks",
      "season": 2026,
      "result": false,
      "point_dif": 1,
      "home_team_score": 3,
      "away_team_score": 4
    }
  ],
  "lastupdated": "2025-12-12T09:17:02.597931"
}