{
  "events": [
    {
      "id": 401803047,
      "datetime": "2026-01-10T02:00:00.000Z",
      "neutral_site": 0,
      "is_postseason": 0,
      "home_team_name": "mammoth",
      "home_team_id": 129764,
      "away_team_name": "blues",
      "away_team_id": 19,
      "home_elo_pre": 1504.2125577001,
      "away_elo_pre": 1467.4210179812,
      "elo_diff": 61.7915397189,
      "elo_spread": -3.1526295775,
      "home_elo_prob": 0.5443457577,
      "away_elo_prob": 0.4556542423,
      "home_elo_post": 1508.1078491998,
      "away_elo_post": 1463.5257264815,
      "tournament_id": null,
      "str_event_id": "20260110_mammoth_blues",
      "season": 2026,
      "result": true,
      "point_dif": -2,
      "home_team_score": 4,
      "away_team_score": 2
    },
    {
      "id": 401803046,
      "datetime": "2026-01-10T01:00:00.000Z",
      "neutral_site": 0,
      "is_postseason": 0,
      "home_team_name": "jets",
      "home_team_id": 28,
      "away_team_name": "kings",
      "away_team_id": 8,
      "home_elo_pre": 1523.8105346037,
      "away_elo_pre": 1523.4941460667,
      "elo_diff": 25.316388537,
      "elo_spread": -1.2916524764,
      "home_elo_prob": 0.5182085501,
      "away_elo_prob": 0.4817914499,
      "home_elo_post": 1529.9432698668,
      "away_elo_post": 1517.3614108036,
      "tournament_id": null,
      "str_event_id": "20260110_jets_kings",
      "season": 2026,
      "result": true,
      "point_dif": -4,
      "home_team_score": 5,
      "away_team_score": 1
    },
    {
      "id": 401803045,
      "datetime": "2026-01-10T01:00:00.000Z",
      "neutral_site": 0,
      "is_postseason": 0,
      "home_team_name": "blackhawks",
      "home_team_id": 4,
      "away_team_name": "capitals",
      "away_team_id": 23,
      "home_elo_pre": 1406.8361336431,
      "away_elo_pre": 1534.8052745301,
      "elo_diff": -102.9691408869,
      "elo_spread": 5.2535275963,
      "home_elo_prob": 0.4264453476,
      "away_elo_prob": 0.5735546524,
      "home_elo_post": 1401.5909323756,
      "away_elo_post": 1540.0504757976,
      "tournament_id": null,
      "str_event_id": "20260110_blackhawks_capitals",
      "season": 2026,
      "result": false,
      "point_dif": 4,
      "home_team_score": 1,
      "away_team_score": 5
    },
    {
      "id": 401803044,
      "datetime": "2026-01-09T03:00:00.000Z",
      "neutral_site": 0,
      "is_postseason": 0,
      "home_team_name": "kraken",
      "home_team_id": 124292,
      "away_team_name": "wild",
      "away_team_id": 30,
      "home_elo_pre": 1478.9696611872,
      "away_elo_pre": 1541.6101040905,
      "elo_diff": -37.6404429032,
      "elo_spread": 1.9204307604,
      "home_elo_prob": 0.4729419842,
      "away_elo_prob": 0.5270580158,
      "home_elo_post": 1476.3912291118,
      "away_elo_post": 1544.1885361659,
      "tournament_id": null,
      "str_event_id": "20260109_kraken_wild",
      "season": 2026,
      "result": false,
      "point_dif": 1,
      "home_team_score": 2,
      "away_team_score": 3
    },
    {
      "id": 401803043,
      "datetime": "2026-01-09T03:00:00.000Z",
      "neutral_site": 0,
      "is_postseason": 0,
      "home_team_name": "goldenknights",
      "home_team_id": 37,
      "away_team_name": "bluejackets",
      "away_team_id": 29,
      "home_elo_pre": 1534.0812555666,
      "away_elo_pre": 1469.6208522729,
      "elo_diff": 89.4604032937,
      "elo_spread": -4.5643062905,
      "home_elo_prob": 0.5640186224,
      "away_elo_prob": 0.4359813776,
      "home_elo_post": 1537.7633245693,
      "away_elo_post": 1465.9387832702,
      "tournament_id": null,
      "str_event_id": "20260109_goldenknights_bluejackets",
      "season": 2026,
      "result": true,
      "point_dif": -2,
      "home_team_score": 5,
      "away_team_score": 3
    },
    {
      "id": 401803042,
      "datetime": "2026-01-09T02:00:00.000Z",
      "neutral_site": 0,
      "is_postseason": 0,
      "home_team_name": "avalanche",
      "home_team_id": 17,
      "away_team_name": "senators",
      "away_team_id": 14,
      "home_elo_pre": 1648.4628828445,
      "away_elo_pre": 1503.3279601967,
      "elo_diff": 170.1349226478,
      "elo_spread": -8.6803531963,
      "home_elo_prob": 0.6200328528,
      "away_elo_prob": 0.3799671472,
      "home_elo_post": 1653.9533390242,
      "away_elo_post": 1497.8375040169,
      "tournament_id": null,
      "str_event_id": "20260109_avalanche_senators",
      "season": 2026,
      "result": true,
      "point_dif": -6,
      "home_team_score": 8,
      "away_team_score": 2
    },
    {
      "id": 401803041,
      "datetime": "2026-01-09T01:00:00.000Z",
      "neutral_site": 0,
      "is_postseason": 0,
      "home_team_name": "jets",
      "home_team_id": 28,
      "away_team_name": "oilers",
      "away_team_id": 6,
      "home_elo_pre": 1526.5599619806,
      "away_elo_pre": 1555.9802669819,
      "elo_diff": -4.4203050013,
      "elo_spread": 0.2255257654,
      "home_elo_prob": 0.4968193778,
      "away_elo_prob": 0.5031806222,
      "home_elo_post": 1523.8105346037,
      "away_elo_post": 1558.7296943588,
      "tournament_id": null,
      "str_event_id": "20260109_jets_oilers",
      "season": 2026,
      "result": false,
      "point_dif": 1,
      "home_team_score": 3,
      "away_team_score": 4
    },
    {
      "id": 401803040,
      "datetime": "2026-01-09T01:00:00.000Z",
      "neutral_site": 0,
      "is_postseason": 0,
      "home_team_name": "predators",
      "home_team_id": 27,
      "away_team_name": "islanders",
      "away_team_id": 12,
      "home_elo_pre": 1450.0930861268,
      "away_elo_pre": 1496.0459724619,
      "elo_diff": -20.9528863351,
      "elo_spread": 1.069024813,
      "home_elo_prob": 0.4849277542,
      "away_elo_prob": 0.5150722458,
      "home_elo_post": 1452.9767169397,
      "away_elo_post": 1493.1623416489,
      "tournament_id": null,
      "str_event_id": "20260109_predators_islanders",
      "season": 2026,
      "result": true,
      "point_dif": -1,
      "home_team_score": 2,
      "away_team_score": 1
    },
    {
      "id": 401803036,
      "datetime": "2026-01-09T00:00:00.000Z",
      "neutral_site": 0,
      "is_postseason": 0,
      "home_team_name": "rangers",
      "home_team_id": 13,
      "away_team_name": "sabres",
      "away_team_id": 2,
      "home_elo_pre": 1510.4130351275,
      "away_elo_pre": 1502.3632559523,
      "elo_diff": 33.0497791752,
      "elo_spread": -1.6862132232,
      "home_elo_prob": 0.5237633114,
      "away_elo_prob": 0.4762366886,
      "home_elo_post": 1504.5157209755,
      "away_elo_post": 1508.2605701043,
      "tournament_id": null,
      "str_event_id": "20260109_rangers_sabres",
      "season": 2026,
      "result": false,
      "point_dif": 3,
      "home_team_score": 2,
      "away_team_score": 5
    },
    {
      "id": 401803033,
      "datetime": "2026-01-09T00:00:00.000Z",
      "neutral_site": 0,
      "is_postseason": 0,
      "home_team_name": "bruins",
      "home_team_id": 1,
      "away_team_name": "flames",
      "away_team_id": 3,
      "home_elo_pre": 1490.3371016496,
      "away_elo_pre": 1478.4573268226,
      "elo_diff": 36.879774827,
      "elo_spread": -1.8816211646,
      "home_elo_prob": 0.5265122419,
      "away_elo_prob": 0.4734877581,
      "home_elo_post": 1495.5016724637,
      "away_elo_post": 1473.2927560086,
      "tournament_id": null,
      "str_event_id": "20260109_bruins_flames",
      "season": 2026,
      "result": true,
      "point_dif": -3,
      "home_team_score": 4,
      "away_team_score": 1
    },
    {
      "id": 401803034,
      "datetime": "2026-01-09T00:00:00.000Z",
      "neutral_site": 0,
      "is_postseason": 0,
      "home_team_name": "canadiens",
      "home_team_id": 10,
      "away_team_name": "panthers",
      "away_team_id": 26,
      "home_elo_pre": 1494.183109229,
      "away_elo_pre": 1566.1853145813,
      "elo_diff": -47.0022053523,
      "elo_spread": 2.3980717016,
      "home_elo_prob": 0.4662306814,
      "away_elo_prob": 0.5337693186,
      "home_elo_post": 1501.205692813,
      "away_elo_post": 1559.1627309973,
      "tournament_id": null,
      "str_event_id": "20260109_canadiens_panthers",
      "season": 2026,
      "result": true,
      "point_dif": -4,
      "home_team_score": 6,
      "away_team_score": 2
    },
    {
      "id": 401803035,
      "datetime": "2026-01-09T00:00:00.000Z",
      "neutral_site": 0,
      "is_postseason": 0,
      "home_team_name": "redwings",
      "home_team_id": 5,
      "away_team_name": "canucks",
      "away_team_id": 22,
      "home_elo_pre": 1498.9044368624,
      "away_elo_pre": 1454.7185557023,
      "elo_diff": 69.1858811601,
      "elo_spread": -3.5298918959,
      "home_elo_prob": 0.5496193846,
      "away_elo_prob": 0.4503806154,
      "home_elo_post": 1504.5265102791,
      "away_elo_post": 1449.0964822855,
      "tournament_id": null,
      "str_event_id": "20260109_redwings_canucks",
      "season": 2026,
      "result": true,
      "point_dif": -4,
      "home_team_score": 5,
      "away_team_score": 1
    },
    {
      "id": 401803038,
      "datetime": "2026-01-09T00:00:00.000Z",
      "neutral_site": 0,
      "is_postseason": 0,
      "home_team_name": "penguins",
      "home_team_id": 16,
      "away_team_name": "devils",
      "away_team_id": 11,
      "home_elo_pre": 1484.7465276956,
      "away_elo_pre": 1479.527613939,
      "elo_diff": 30.2189137566,
      "elo_spread": -1.5417813141,
      "home_elo_prob": 0.5217305588,
      "away_elo_prob": 0.4782694412,
      "home_elo_post": 1489.9788352358,
      "away_elo_post": 1474.2953063988,
      "tournament_id": null,
      "str_event_id": "20260109_penguins_devils",
      "season": 2026,
      "result": true,
      "point_dif": -3,
      "home_team_score": 4,
      "away_team_score": 1
    },
    {
      "id": 401803039,
      "datetime": "2026-01-09T00:00:00.000Z",
      "neutral_site": 0,
      "is_postseason": 0,
      "home_team_name": "hurricanes",
      "home_team_id": 7,
      "away_team_name": "ducks",
      "away_team_id": 25,
      "home_elo_pre": 1570.8920666732,
      "away_elo_pre": 1435.1237453474,
      "elo_diff": 160.7683213258,
      "elo_spread": -8.2024653738,
      "home_elo_prob": 0.6136612345,
      "away_elo_prob": 0.3863387655,
      "home_elo_post": 1574.8849171158,
      "away_elo_post": 1431.1308949047,
      "tournament_id": null,
      "str_event_id": "20260109_hurricanes_ducks",
      "season": 2026,
      "result": true,
      "point_dif": -3,
      "home_team_score": 5,
      "away_team_score": 2
    },
    {
      "id": 401803037,
      "datetime": "2026-01-09T00:00:00.000Z",
      "neutral_site": 0,
      "is_postseason": 0,
      "home_team_name": "flyers",
      "home_team_id": 15,
      "away_team_name": "mapleleafs",
      "away_team_id": 21,
      "home_elo_pre": 1480.0176052333,
      "away_elo_pre": 1541.92497864,
      "elo_diff": -36.9073734066,
      "elo_spread": 1.8830292554,
      "home_elo_prob": 0.4734679552,
      "away_elo_prob": 0.5265320448,
      "home_elo_post": 1477.4354596849,
      "away_elo_post": 1544.5071241884,
      "tournament_id": null,
      "str_event_id": "20260109_flyers_mapleleafs",
      "season": 2026,
      "result": false,
      "point_dif": 1,
      "home_team_score": 1,
      "away_team_score": 2
    },
    {
      "id": 401803032,
      "datetime": "2026-01-08T03:30:00.000Z",
      "neutral_site": 0,
      "is_postseason": 0,
      "home_team_name": "kings",
      "home_team_id": 8,
      "away_team_name": "sharks",
      "away_team_id": 18,
      "home_elo_pre": 1527.1515646249,
      "away_elo_pre": 1393.71628315,
      "elo_diff": 158.4352814749,
      "elo_spread": -8.0834327283,
      "home_elo_prob": 0.612068018,
      "away_elo_prob": 0.387931982,
      "home_elo_post": 1523.4941460667,
      "away_elo_post": 1397.3737017082,
      "tournament_id": null,
      "str_event_id": "20260108_kings_sharks",
      "season": 2026,
      "result": false,
      "point_dif": 1,
      "home_team_score": 3,
      "away_team_score": 4
    },
    {
      "id": 401803031,
      "datetime": "2026-01-08T02:30:00.000Z",
      "neutral_site": 0,
      "is_postseason": 0,
      "home_team_name": "mammoth",
      "home_team_id": 129764,
      "away_team_name": "senators",
      "away_team_id": 14,
      "home_elo_pre": 1499.9616035791,
      "away_elo_pre": 1507.5789143177,
      "elo_diff": 17.3826892614,
      "elo_spread": -0.8868719011,
      "home_elo_prob": 0.5125052419,
      "away_elo_prob": 0.4874947581,
      "home_elo_post": 1504.2125577001,
      "away_elo_post": 1503.3279601967,
      "tournament_id": null,
      "str_event_id": "20260108_mammoth_senators",
      "season": 2026,
      "result": true,
      "point_dif": -2,
      "home_team_score": 3,
      "away_team_score": 1
    },
    {
      "id": 401803030,
      "datetime": "2026-01-08T02:30:00.000Z",
      "neutral_site": 0,
      "is_postseason": 0,
      "home_team_name": "blackhawks",
      "home_team_id": 4,
      "away_team_name": "blues",
      "away_team_id": 19,
      "home_elo_pre": 1399.7793096704,
      "away_elo_pre": 1474.477841954,
      "elo_diff": -49.6985322836,
      "elo_spread": 2.5356394022,
      "home_elo_prob": 0.4642998839,
      "away_elo_prob": 0.5357001161,
      "home_elo_post": 1406.8361336431,
      "away_elo_post": 1467.4210179812,
      "tournament_id": null,
      "str_event_id": "20260108_blackhawks_blues",
      "season": 2026,
      "result": true,
      "point_dif": -4,
      "home_team_score": 7,
      "away_team_score": 3
    },
    {
      "id": 401803029,
      "datetime": "2026-01-08T00:30:00.000Z",
      "neutral_site": 0,
      "is_postseason": 0,
      "home_team_name": "canadiens",
      "home_team_id": 10,
      "away_team_name": "flames",
      "away_team_id": 3,
      "home_elo_pre": 1488.9512417839,
      "away_elo_pre": 1483.6891942677,
      "elo_diff": 30.2620475162,
      "elo_spread": -1.5439820161,
      "home_elo_prob": 0.5217615373,
      "away_elo_prob": 0.4782384627,
      "home_elo_post": 1494.183109229,
      "away_elo_post": 1478.4573268226,
      "tournament_id": null,
      "str_event_id": "20260108_canadiens_flames",
      "season": 2026,
      "result": true,
      "point_dif": -3,
      "home_team_score": 4,
      "away_team_score": 1
    },
    {
      "id": 401803028,
      "datetime": "2026-01-08T00:00:00.000Z",
      "neutral_site": 0,
      "is_postseason": 0,
      "home_team_name": "capitals",
      "home_team_id": 23,
      "away_team_name": "stars",
      "away_team_id": 9,
      "home_elo_pre": 1540.3037542058,
      "away_elo_pre": 1569.7599239712,
      "elo_diff": -4.4561697654,
      "elo_spread": 0.2273556003,
      "home_elo_prob": 0.4967935721,
      "away_elo_prob": 0.5032064279,
      "home_elo_post": 1534.8052745301,
      "away_elo_post": 1575.2584036469,
      "tournament_id": null,
      "str_event_id": "20260108_capitals_stars",
      "season": 2026,
      "result": false,
      "point_dif": 3,
      "home_team_score": 1,
      "away_team_score": 4
    }
  ],
  "lastupdated": "2026-01-10T09:12:10.374280"
}